Workbook
Name AE_rates: 'AE Model'!$B$40:$E$47
Name AgreeMap: 'AE Feb Model'!$Q$3:$R$8

Sheet AE Calculator
B1: Unit Goal | C1: AE Target | D1: Access | E1: Shared Marketing | F1: Exclusive Marketing | G1: Exclusive Marketing with BS NOW | H1: Bulk | I1: Winback
A2: AE | B2: 500 | C2: 3333.33 | D2: 0.5 | E2: 0.75 | F2: 1 | G2: 1.25 | H2: 1.4 | I2: 1.6
A3: Dollars per Unit Target | B3: =C2/B2 -> 6.66666
A5: (example Month) | B5: Units | C5: Type | D5: Multiplier | E5: Payout | G5: Next Steps
A6: Deal 1 | B6: 120 | C6: Access | D6: 0.5 | E6: =(B6*B3)*D6 -> 399.9996 | G6: Relook the AE territories to give everyone equal opportunity regardless of location
A7: Deal 2 | B7: 150 | C7: EM/wBSNOW | D7: 1.25 | E7: =(B7*B3)*D7 -> 1249.9987 | G7: Meet with comp team to determine what's possible.
A8: Deal 3 | B8: 55 | C8: Bulk | D8: 1.4 | E8: =(B8*B3)*D8 -> 513.33282 | G8: Align with weightings and categories for accelerators and decelerators
A9: Deal 4 | B9: 75 | C9: Winback | D9: 1.6 | E9: =(B9*B3)*D9 -> 799.9992
A10: Deal 5 | B10: 200 | C10: Bulk | D10: 1.4 | E10: =(B10*B3)*D10 -> 1866.6648
A13: Totals | B13: =SUM(B6:B12) -> 600 | E13: =SUM(E6:E12) -> 4829.9952
E15: (Logic: Payout = Units X $$'s X Unit Target X Multiplier
A17: AE Target | B17: 40k per year commission

Sheet Sheet2
B4: MDU Contracted Units Assumptions
C5: Monthly Quota | D5: Units per Contract | E5: Total Contracted Units
B6: 46023 | C6: 27 | D6: 138 | E6: 3726
B7: 46054 | C7: 27 | D7: 138 | E7: 3726
B8: 46082 | C8: 27 | D8: 138 | E8: 3726
B9: 46113 | C9: 27 | D9: 138 | E9: 3726
B10: 46143 | C10: 27 | D10: 138 | E10: 3726
B11: 46174 | C11: 27 | D11: 138 | E11: 3726
B12: 46204 | C12: 27 | D12: 138 | E12: 3726
B13: 46235 | C13: 27 | D13: 138 | E13: 3726
B14: 46266 | C14: 27 | D14: 138 | E14: 3726
B15: 46296 | C15: 27 | D15: 138 | E15: 3726
B16: 46327 | C16: 27 | D16: 138 | E16: 3726
B17: 46357 | C17: 27 | D17: 138 | E17: 3726
B18: Total Subs: | E18: =SUM(E6:E17) -> 44712

Sheet Summary
C3: AE Plan
C4: [Account Manager] | D4: Role | E4: Jan Paid | F4: Jan Model | G4: Var | H4: Feb Model
C5: Adam Sivertson | D5: AE | E5: ='AE Jan Model'!O4 -> 3250 | F5: ='AE Jan Model'!P4 -> 1475.52 | G5: ='AE Jan Model'!Q4 -> -1774.48 | H5: ='AE Jan Model'!S4 -> 0
C6: Amir Planes | D6: AE | E6: ='AE Jan Model'!O5 -> 4000 | F6: ='AE Jan Model'!P5 -> 3562.65 | G6: ='AE Jan Model'!Q5 -> -437.35 | H6: ='AE Jan Model'!S5 -> 0
C7: Constance James | D7: AE | E7: ='AE Jan Model'!O6 -> 3250 | F7: ='AE Jan Model'!P6 -> 995.28 | G7: ='AE Jan Model'!Q6 -> -2254.72 | H7: ='AE Jan Model'!S6 -> 0
C8: Deanna Bethea | D8: AE | E8: ='AE Jan Model'!O7 -> 11050 | F8: ='AE Jan Model'!P7 -> 4494.42 | G8: ='AE Jan Model'!Q7 -> -6555.58 | H8: ='AE Jan Model'!S7 -> 555.06
C9: Guy Huntley | D9: AE | E9: ='AE Jan Model'!O8 -> 0 | F9: ='AE Jan Model'!P8 -> 0 | G9: ='AE Jan Model'!Q8 -> 0 | H9: ='AE Jan Model'!S8 -> 1144.92
C10: Jennifer Raypole | D10: AE | E10: ='AE Jan Model'!O9 -> 12300 | F10: ='AE Jan Model'!P9 -> 7669.42 | G10: ='AE Jan Model'!Q9 -> -4630.58 | H10: ='AE Jan Model'!S9 -> 344.52
C11: Steve Norris | D11: AE | E11: ='AE Jan Model'!O10 -> 2500 | F11: ='AE Jan Model'!P10 -> 1315.44 | G11: ='AE Jan Model'!Q10 -> -1184.56 | H11: ='AE Jan Model'!S10 -> 0
C12: Todd Myers | D12: AE | E12: ='AE Jan Model'!O11 -> 8000 | F12: ='AE Jan Model'!P11 -> 2490.81 | G12: ='AE Jan Model'!Q11 -> -5509.19 | H12: ='AE Jan Model'!S11 -> 2976.27
C13: Morgan Carper | D13: Natl AE | E13: ='AE Jan Model'!O12 -> 0 | F13: ='AE Jan Model'!P12 -> 0 | G13: ='AE Jan Model'!Q12 -> 0 | H13: ='AE Jan Model'!S12 -> 6892.644
C14: Total | E14: =SUM(E5:E13) -> 44350 | F14: =SUM(F5:F13) -> 22003.54 | G14: =SUM(G5:G13) -> -22346.46 | H14: =SUM(H5:H13) -> 11913.414
C16: Jason Herdrich | D16: Sr. Manager | E16: ='AE Jan Model'!O15 -> 0 | F16: ='AE Jan Model'!P15 -> 3740.9793 | G16: ='AE Jan Model'!Q15 -> 0 | H16: ='AE Jan Model'!S15 -> 1725.1148
C18: TSR Plan
C19: TSR | D19: Role | E19: Jan Paid | F19: Jan Model | G19: Var | H19: Feb Model
C20: Freddy Morales | D20: TSR MDU | E20: ='TSR Sales Feb Model'!S28 -> 2435.8333 | F20: ='TSR Sales Feb Model'!T28 -> 2574.7755 | G20: ='TSR Sales Feb Model'!U28 -> 138.94213 | H20: ='TSR Sales Feb Model'!P28 -> 2013.5579
C21: Joseph Buckles | D21: TSR MDU | E21: ='TSR Sales Feb Model'!S29 -> 1969.1667 | F21: ='TSR Sales Feb Model'!T29 -> 2151.7366 | G21: ='TSR Sales Feb Model'!U29 -> 182.56995 | H21: ='TSR Sales Feb Model'!P29 -> 1833.8821
C22: Karsten Freeman | D22: TSR MDU | E22: ='TSR Sales Feb Model'!S30 -> 2307.5 | F22: ='TSR Sales Feb Model'!T30 -> 2370.672 | G22: ='TSR Sales Feb Model'!U30 -> 63.172022 | H22: ='TSR Sales Feb Model'!P30 -> 1777.9068
C23: Name TBD | D23: TSR SFU | E23: ='TSR Sales Feb Model'!S31 -> 0 | F23: ='TSR Sales Feb Model'!T31 -> 3166.1596 | G23: ='TSR Sales Feb Model'!U31 -> 3166.1596 | H23: ='TSR Sales Feb Model'!P31 -> 2376.0305
E24: =SUM(E20:E23) -> 6712.5 | F24: =SUM(F20:F23) -> 10263.344 | G24: =SUM(G20:G23) -> 3550.8437 | H24: =SUM(H20:H23) -> 8001.3773
C26: Norman Mundy | D26: Sr. Mgr | E26: ='TSR Sales Feb Model'!S34 -> 4284.8333 | F26: ='TSR Sales Feb Model'!T34 -> 4270.2033 | G26: ='TSR Sales Feb Model'!U34 -> -14.630016 | H26: ='TSR Sales Feb Model'!P34 -> 3327.7328
C29: DIR PLAN
C30: TSR | D30: Role | E30: Jan Paid | F30: Jan Model | G30: Var | H30: Feb Model
C31: Megan | D31: Director | E31: ='Dir Model'!G21 -> 5328.8236 | F31: ='Dir Model'!G20 -> 4953.1565 | G31: =F31-E31 -> -375.66711 | H31: ='Dir Model'!G29 -> 3235.0983

Sheet AE Model
B2: AE Targets | C2: Role | D2: Jan | E2: Feb | F2: Mar | G2: Apr | H2: May | I2: Jun | J2: Jul | K2: Aug | L2: Sep | M2: Oct | N2: Nov | O2: Dec | P2: Total
B3: Units Contracted | C3: Budget | D3: =27*138 -> 3726 | E3: =27*138 -> 3726 | F3: =27*138 -> 3726 | G3: =27*138 -> 3726 | H3: =27*138 -> 3726 | I3: =27*138 -> 3726 | J3: =27*138 -> 3726 | K3: =27*138 -> 3726 | ... O3: =27*138 -> 3726 | P3: =SUM(D3:O3) -> 44712
C4: Target @ 90% | D4: =D3*0.9 -> 3353.4 | E4: =E3*0.9 -> 3353.4 | F4: =F3*0.9 -> 3353.4 | G4: =G3*0.9 -> 3353.4 | H4: =H3*0.9 -> 3353.4 | I4: =I3*0.9 -> 3353.4 | J4: =J3*0.9 -> 3353.4 | K4: =K3*0.9 -> 3353.4 | ... O4: =O3*0.9 -> 3353.4 | P4: =SUM(D4:O4) -> 40240.8
B5: Commission Targets
B6: Per Rep | C6: AE | D6: 383 | E6: 383 | F6: 383 | G6: 383 | H6: 383 | I6: 383 | J6: 383 | K6: 383 | L6: 383 | M6: 383 | N6: 383 | O6: 383 | P6: =SUM(D6:O6) -> 4596
B7: Natl AE | C7: Natl AE | D7: 300 | E7: 300 | F7: 300 | G7: 300 | H7: 300 | I7: 300 | J7: 300 | K7: 300 | L7: 300 | M7: 300 | N7: 300 | O7: 300 | P7: =SUM(D7:O7) -> 3600
B8: 8 AEs + 1 Natl AE | C8: Sr. Mgr | D8: =(D6*8)+D7 -> 3364 | E8: =(E6*8)+E7 -> 3364 | F8: =(F6*8)+F7 -> 3364 | G8: =(G6*8)+G7 -> 3364 | H8: =(H6*8)+H7 -> 3364 | I8: =(I6*8)+I7 -> 3364 | J8: =(J6*8)+J7 -> 3364 | K8: =(K6*8)+K7 -> 3364 | ... O8: =(O6*8)+O7 -> 3364 | P8: =SUM(D8:O8) -> 40368
B9: Budget Target | C9: Director, Sr. Director | D9: =D3 -> 3726 | E9: =E3 -> 3726 | F9: =F3 -> 3726 | G9: =G3 -> 3726 | H9: =H3 -> 3726 | I9: =I3 -> 3726 | J9: =J3 -> 3726 | K9: =K3 -> 3726 | ... O9: =O3 -> 3726 | P9: =SUM(D9:O9) -> 44712
B10: For launch, plan is to keep monthly goals even (as shown). May look at adjusting for seasonality in Q3/Q4 (or going into 2027)
D12: =L14 -> 8.7 | E12: =L15 -> 11.11 | H12: Proposed Rates > To be modeled to confirm (may want to round off)
B13: Rate Card (Contract Type) | C13: Role | D13: AE Rate | E13: Natl AE Rate | F13: Rate Mult | H13: Role | I13: TSI | J13: AE Target | K13: Per Unit Rate | L13: Rate Card
A14: Access | B14: Access Agreement | C14: AE, Natl AE | D14: =D$12*F14 -> 6.09 | E14: =E$12*F14 -> 7.777 | F14: 0.7 | H14: AE | I14: =40000/12 -> 3333.3333 | J14: =D6 -> 383 | K14: =I14/J14 -> 8.7032202 | L14: =ROUND(K14,2) -> 8.7
A15: Shared | B15: Shared Marketing | C15: AE, Natl AE | D15: =D$12*F15 -> 7.83 | E15: =E$12*F15 -> 9.999 | F15: 0.9 | H15: Natl AE | I15: =40000/12 -> 3333.3333 | J15: =D7 -> 300 | K15: =I15/J15 -> 11.111111 | L15: =ROUND(K15,2) -> 11.11
A16: Exclusive | B16: Exclusive Marketing | C16: AE, Natl AE | D16: =D$12*F16 -> 9.57 | E16: =E$12*F16 -> 12.221 | F16: 1.1
A17: Bulk | B17: Bulk Agreement | C17: AE, Natl AE | D17: =D$12*F17 -> 12.18 | E17: =E$12*F17 -> 15.554 | F17: 1.4
B19: Winback Type removed
B20: Exclusive Marketing with BS NOW removed
D21: AE Rate | E21: Natl AE Rate
B22: 5 Contract Bonus (Exclusive or Bulk) | D22: 1000 | E22: 1000 | F22: 5 Contracts that are Exclusive or Bulk with a min of 50 Contracted Units per contract
C25: Components & Weight | F25: Thresholds
B26: Roles | C26: Units Contracted | D26: Plan Math | E26: Target Y/N | F26: Min | G26: Max
B27: AE | C27: 100% TSI | D27: Units x Rate | E27: N | F27: None | G27: 300% of TSI
B28: Natl AE | C28: 100% TSI | D28: Units x Rate | E28: N | F28: None | G28: 300% of TSI
B29: Sr Mgr | C29: 100% TSI | D29: % Attain to Target | E29: Y | F29: None | G29: 200% of TSI
B32: Eligible Transactions for Earnings
B33: AE | C33: Excel version of Salesforce report, attributed to rep, and deemed eligible by Steve/Megan
B34: Natl AE | C34: Excel version of Salesforce report, attributed to rep, and deemed eligible by Steve/Megan
B35: Sr. Manager | C35: Aggregation of all eligible transactions, summed and calculated as a % attainment to target
B39: Rate Table
B40: =C40&" "&D40 -> Access AE | C40: Access | D40: AE | E40: =D14 -> 6.09
B41: =C41&" "&D41 -> Access Natl AE | C41: Access | D41: Natl AE | E41: =E14 -> 7.777
B42: =C42&" "&D42 -> Shared AE | C42: Shared | D42: AE | E42: =D15 -> 7.83
B43: =C43&" "&D43 -> Shared Natl AE | C43: Shared | D43: Natl AE | E43: =E15 -> 9.999
B44: =C44&" "&D44 -> Exclusive AE | C44: Exclusive | D44: AE | E44: =D16 -> 9.57
B45: =C45&" "&D45 -> Exclusive Natl AE | C45: Exclusive | D45: Natl AE | E45: =E16 -> 12.221
B46: =C46&" "&D46 -> Bulk AE | C46: Bulk | D46: AE | E46: =D17 -> 12.18
B47: =C47&" "&D47 -> Bulk Natl AE | C47: Bulk | D47: Natl AE | E47: =E17 -> 15.554

Sheet AE Contracts Feb Sample
A1: [Account Manager] | B1: [Account] | C1: [Opportunity] | D1: [Offer #] | E1: [Offer Type] | F1: [Sub Type] | G1: [Contract Status] | H1: [Contract Executed Date] | I1: [Contracted Units]
A2: Deanna Bethea | B2: Nash Portfolio LLC/Bailey MHP LLC | C2: Bailey MHP | D2: OR-057056 | E2: Exclusive Marketing | F2: New Service | G2: Contract Executed | H2: 46058 | I2: 58
A3: Guy Huntley | B3: CIRCLE H HOLDINGS, LLC | C3: Lone Star Prairie | D3: OR-057360 | E3: BAA | F3: New Service | G3: Contract Executed | H3: 46063 | I3: 188
A4: Guy Huntley | B4: JJR Development, LLC | C4: Savannah Place | D4: OR-057292 | E4: Exclusive Marketing | F4: New Service | G4: Contract Executed | H4: 46070 | I4: 116
A5: Jennifer Raypole | B5: EMH Cattle Company | C5: Oak Tree East Apartments | D5: OR-057354 | E5: Exclusive Marketing | F5: New Service | G5: Contract Executed | H5: 46071 | I5: 74
A6: Jennifer Raypole | B6: Fullingim Developments, LLC | C6: Park 19 | D6: OR-057246 | E6: Sole Provider | F6: New Service | G6: Contract Executed | H6: 46064 | I6: 36
A7: Morgan Carper | B7: Jones Estates The Oaks LLC | C7: The Oaks | D7: OR-057278 | E7: Exclusive Marketing | F7: New Service | G7: Contract Executed | H7: 46058 | I7: 119
A8: Morgan Carper | B8: DR Horton, Inc. | C8: Iron Horse | D8: OR-057344 | E8: Exclusive Marketing | F8: New Service | G8: Contract Executed | H8: 46055 | I8: 277
A9: Todd Myers | B9: Jones Estates Rolling Valley PA LLC | C9: Rolling Valley Estates | D9: OR-057272 | E9: Exclusive Marketing | F9: New Service | G9: Contract Executed | H9: 46058 | I9: 76
A10: Todd Myers | B10: Jones Estates Pinehurst Manor PA LLC | C10: Pinehurst Manor | D10: OR-057274 | E10: Exclusive Marketing | F10: New Service | G10: Contract Executed | H10: 46058 | I10: 53
A11: Todd Myers | B11: Jones Estates Woodland Meadows PA LLC | C11: Woodland Meadows | D11: OR-057271 | E11: Exclusive Marketing | F11: New Service | G11: Contract Executed | H11: 46058 | I11: 58
A15: Data provided by Hary Toledo
A16: Sample data provided 2.19.26
A17: Automated email send : last day of the month at 11:50pm (+/- 10 mins). This will be the final data set for the month.
B21: email address
B22: salesforce ID
B23: payroll ID

Sheet AE Feb Model
B1: [Account Manager] | C1: [Related Offer: Offer Name] | D1: [Offer Type] | E1: Agreement | F1: [Contracted Units]
B2: Deanna Bethea | C2: OR-057056 | D2: Exclusive Marketing | E2: =VLOOKUP(D2,AgreeMap,2,FALSE) -> Exclusive | F2: 58
B3: Guy Huntley | C3: OR-057360 | D3: BAA | E3: =VLOOKUP(D3,AgreeMap,2,FALSE) -> Access | F3: 188 | Q3: BEA Only | R3: Access
B4: Jennifer Raypole | C4: OR-057246 | D4: Sole Provider | E4: =VLOOKUP(D4,AgreeMap,2,FALSE) -> Exclusive | F4: 36 | Q4: BAA | R4: Access
B5: Morgan Carper | C5: OR-057276 | D5: Exclusive Marketing | E5: =VLOOKUP(D5,AgreeMap,2,FALSE) -> Exclusive | F5: 119 | Q5: Bulk | R5: Bulk
B6: Morgan Carper | C6: OR-057277 | D6: Exclusive Marketing | E6: =VLOOKUP(D6,AgreeMap,2,FALSE) -> Exclusive | F6: 49 | Q6: Sole Provider | R6: Exclusive
B7: Morgan Carper | C7: OR-057278 | D7: Exclusive Marketing | E7: =VLOOKUP(D7,AgreeMap,2,FALSE) -> Exclusive | F7: 119 | Q7: Shared Marketing | R7: Shared
B8: Morgan Carper | C8: OR-057344 | D8: Exclusive Marketing | E8: =VLOOKUP(D8,AgreeMap,2,FALSE) -> Exclusive | F8: 277 | Q8: Exclusive Marketing | R8: Exclusive
B9: Todd Myers | C9: OR-057271 | D9: Exclusive Marketing | E9: =VLOOKUP(D9,AgreeMap,2,FALSE) -> Exclusive | F9: 58
B10: Todd Myers | C10: OR-057272 | D10: Exclusive Marketing | E10: =VLOOKUP(D10,AgreeMap,2,FALSE) -> Exclusive | F10: 76
B11: Todd Myers | C11: OR-057273 | D11: Exclusive Marketing | E11: =VLOOKUP(D11,AgreeMap,2,FALSE) -> Exclusive | F11: 124
B12: Todd Myers | C12: OR-057274 | D12: Exclusive Marketing | E12: =VLOOKUP(D12,AgreeMap,2,FALSE) -> Exclusive | F12: 53
F13: =SUM(F2:F12) -> 1157
J15: Total Agreements | N15: Portfolio Contribution
B16: [Account Manager] | C16: Role | D16: Tot Agreements | E16: Contracted Units | F16: Commission | G16: Units Target | H16: Units Attain | J16: Access | K16: Exclusive | L16: Shared | M16: Bulk | N16: Access | O16: Exclusive | P16: Shared | Q16: Bulk | R16: TSI | S16: % to TSI | V16: Evaluation
B17: Adam Sivertson | C17: AE | D17: =SUMIF($B$31:$B$45,$B17,$E$31:$E$45) -> 0 | E17: =SUMIF($B$31:$B$45,$B17,$F$31:$F$45) -> 0 | F17: =MIN(3*R17,SUMIF($B$31:$B$45,$B17,$H$31:$H$45)) -> 0 | G17: ='AE Model'!$J$14 -> 383 | H17: =E17/G17 -> 0 | J17: =SUMIFS($E$31:$E$45,$D$31:$D$45,J$16,$B$31:$B$45,$B17) -> 0 | K17: =SUMIFS($E$31:$E$45,$D$31:$D$45,K$16,$B$31:$B$45,$B17) -> 0 | L17: =SUMIFS($E$31:$E$45,$D$31:$D$45,L$16,$B$31:$B$45,$B17) -> 0 | M17: =SUMIFS($E$31:$E$45,$D$31:$D$45,M$16,$B$31:$B$45,$B17) -> 0 | N17: =IFERROR(J17/$D17,"") | O17: =IFERROR(K17/$D17,"") | P17: =IFERROR(L17/$D17,"") | Q17: =IFERROR(M17/$D17,"") | R17: ='AE Model'!$I$14 -> 3333.3333 | S17: =F17/R17 -> 0 | V17: ="Units Attain "&TEXT(H17,"0%")&" | % Exclusive "&TEXT(O17,"0%")&" | % to TSI "&TEXT(S17,"0%") -> Units Attain 0% | % Exclusive | % to TSI 0%
B18: Amir Planes | C18: AE | D18: =SUMIF($B$31:$B$45,$B18,$E$31:$E$45) -> 0 | E18: =SUMIF($B$31:$B$45,$B18,$F$31:$F$45) -> 0 | F18: =MIN(3*R18,SUMIF($B$31:$B$45,$B18,$H$31:$H$45)) -> 0 | G18: ='AE Model'!$J$14 -> 383 | H18: =E18/G18 -> 0 | J18: =SUMIFS($E$31:$E$45,$D$31:$D$45,J$16,$B$31:$B$45,$B18) -> 0 | K18: =SUMIFS($E$31:$E$45,$D$31:$D$45,K$16,$B$31:$B$45,$B18) -> 0 | L18: =SUMIFS($E$31:$E$45,$D$31:$D$45,L$16,$B$31:$B$45,$B18) -> 0 | M18: =SUMIFS($E$31:$E$45,$D$31:$D$45,M$16,$B$31:$B$45,$B18) -> 0 | N18: =IFERROR(J18/$D18,"") | O18: =IFERROR(K18/$D18,"") | P18: =IFERROR(L18/$D18,"") | Q18: =IFERROR(M18/$D18,"") | R18: ='AE Model'!$I$14 -> 3333.3333 | S18: =F18/R18 -> 0 | V18: ="Units Attain "&TEXT(H18,"0%")&" | % Exclusive "&TEXT(O18,"0%")&" | % to TSI "&TEXT(S18,"0%") -> Units Attain 0% | % Exclusive | % to TSI 0%
B19: Constance James | C19: AE | D19: =SUMIF($B$31:$B$45,$B19,$E$31:$E$45) -> 0 | E19: =SUMIF($B$31:$B$45,$B19,$F$31:$F$45) -> 0 | F19: =MIN(3*R19,SUMIF($B$31:$B$45,$B19,$H$31:$H$45)) -> 0 | G19: ='AE Model'!$J$14 -> 383 | H19: =E19/G19 -> 0 | J19: =SUMIFS($E$31:$E$45,$D$31:$D$45,J$16,$B$31:$B$45,$B19) -> 0 | K19: =SUMIFS($E$31:$E$45,$D$31:$D$45,K$16,$B$31:$B$45,$B19) -> 0 | L19: =SUMIFS($E$31:$E$45,$D$31:$D$45,L$16,$B$31:$B$45,$B19) -> 0 | M19: =SUMIFS($E$31:$E$45,$D$31:$D$45,M$16,$B$31:$B$45,$B19) -> 0 | N19: =IFERROR(J19/$D19,"") | O19: =IFERROR(K19/$D19,"") | P19: =IFERROR(L19/$D19,"") | Q19: =IFERROR(M19/$D19,"") | R19: ='AE Model'!$I$14 -> 3333.3333 | S19: =F19/R19 -> 0 | V19: ="Units Attain "&TEXT(H19,"0%")&" | % Exclusive "&TEXT(O19,"0%")&" | % to TSI "&TEXT(S19,"0%") -> Units Attain 0% | % Exclusive | % to TSI 0%
B20: Deanna Bethea | C20: AE | D20: =SUMIF($B$31:$B$45,$B20,$E$31:$E$45) -> 1 | E20: =SUMIF($B$31:$B$45,$B20,$F$31:$F$45) -> 58 | F20: =MIN(3*R20,SUMIF($B$31:$B$45,$B20,$H$31:$H$45)) -> 555.06 | G20: ='AE Model'!$J$14 -> 383 | H20: =E20/G20 -> 0.15143603 | J20: =SUMIFS($E$31:$E$45,$D$31:$D$45,J$16,$B$31:$B$45,$B20) -> 0 | K20: =SUMIFS($E$31:$E$45,$D$31:$D$45,K$16,$B$31:$B$45,$B20) -> 1 | L20: =SUMIFS($E$31:$E$45,$D$31:$D$45,L$16,$B$31:$B$45,$B20) -> 0 | M20: =SUMIFS($E$31:$E$45,$D$31:$D$45,M$16,$B$31:$B$45,$B20) -> 0 | N20: =IFERROR(J20/$D20,"") -> 0 | O20: =IFERROR(K20/$D20,"") -> 1 | P20: =IFERROR(L20/$D20,"") -> 0 | Q20: =IFERROR(M20/$D20,"") -> 0 | R20: ='AE Model'!$I$14 -> 3333.3333 | S20: =F20/R20 -> 0.166518 | V20: ="Units Attain "&TEXT(H20,"0%")&" | % Exclusive "&TEXT(O20,"0%")&" | % to TSI "&TEXT(S20,"0%") -> Units Attain 15% | % Exclusive 100% | % to TSI 17%
B21: Guy Huntley | C21: AE | D21: =SUMIF($B$31:$B$45,$B21,$E$31:$E$45) -> 1 | E21: =SUMIF($B$31:$B$45,$B21,$F$31:$F$45) -> 188 | F21: =MIN(3*R21,SUMIF($B$31:$B$45,$B21,$H$31:$H$45)) -> 1144.92 | G21: ='AE Model'!$J$14 -> 383 | H21: =E21/G21 -> 0.49086162 | J21: =SUMIFS($E$31:$E$45,$D$31:$D$45,J$16,$B$31:$B$45,$B21) -> 1 | K21: =SUMIFS($E$31:$E$45,$D$31:$D$45,K$16,$B$31:$B$45,$B21) -> 0 | L21: =SUMIFS($E$31:$E$45,$D$31:$D$45,L$16,$B$31:$B$45,$B21) -> 0 | M21: =SUMIFS($E$31:$E$45,$D$31:$D$45,M$16,$B$31:$B$45,$B21) -> 0 | N21: =IFERROR(J21/$D21,"") -> 1 | O21: =IFERROR(K21/$D21,"") -> 0 | P21: =IFERROR(L21/$D21,"") -> 0 | Q21: =IFERROR(M21/$D21,"") -> 0 | R21: ='AE Model'!$I$14 -> 3333.3333 | S21: =F21/R21 -> 0.343476 | V21: ="Units Attain "&TEXT(H21,"0%")&" | % Exclusive "&TEXT(O21,"0%")&" | % to TSI "&TEXT(S21,"0%") -> Units Attain 49% | % Exclusive 0% | % to TSI 34%
B22: Jennifer Raypole | C22: AE | D22: =SUMIF($B$31:$B$45,$B22,$E$31:$E$45) -> 1 | E22: =SUMIF($B$31:$B$45,$B22,$F$31:$F$45) -> 36 | F22: =MIN(3*R22,SUMIF($B$31:$B$45,$B22,$H$31:$H$45)) -> 344.52 | G22: ='AE Model'!$J$14 -> 383 | H22: =E22/G22 -> 0.093994778 | J22: =SUMIFS($E$31:$E$45,$D$31:$D$45,J$16,$B$31:$B$45,$B22) -> 0 | K22: =SUMIFS($E$31:$E$45,$D$31:$D$45,K$16,$B$31:$B$45,$B22) -> 1 | L22: =SUMIFS($E$31:$E$45,$D$31:$D$45,L$16,$B$31:$B$45,$B22) -> 0 | M22: =SUMIFS($E$31:$E$45,$D$31:$D$45,M$16,$B$31:$B$45,$B22) -> 0 | N22: =IFERROR(J22/$D22,"") -> 0 | O22: =IFERROR(K22/$D22,"") -> 1 | P22: =IFERROR(L22/$D22,"") -> 0 | Q22: =IFERROR(M22/$D22,"") -> 0 | R22: ='AE Model'!$I$14 -> 3333.3333 | S22: =F22/R22 -> 0.103356 | V22: ="Units Attain "&TEXT(H22,"0%")&" | % Exclusive "&TEXT(O22,"0%")&" | % to TSI "&TEXT(S22,"0%") -> Units Attain 9% | % Exclusive 100% | % to TSI 10%
B23: Steve Norris | C23: AE | D23: =SUMIF($B$31:$B$45,$B23,$E$31:$E$45) -> 0 | E23: =SUMIF($B$31:$B$45,$B23,$F$31:$F$45) -> 0 | F23: =MIN(3*R23,SUMIF($B$31:$B$45,$B23,$H$31:$H$45)) -> 0 | G23: ='AE Model'!$J$14 -> 383 | H23: =E23/G23 -> 0 | J23: =SUMIFS($E$31:$E$45,$D$31:$D$45,J$16,$B$31:$B$45,$B23) -> 0 | K23: =SUMIFS($E$31:$E$45,$D$31:$D$45,K$16,$B$31:$B$45,$B23) -> 0 | L23: =SUMIFS($E$31:$E$45,$D$31:$D$45,L$16,$B$31:$B$45,$B23) -> 0 | M23: =SUMIFS($E$31:$E$45,$D$31:$D$45,M$16,$B$31:$B$45,$B23) -> 0 | N23: =IFERROR(J23/$D23,"") | O23: =IFERROR(K23/$D23,"") | P23: =IFERROR(L23/$D23,"") | Q23: =IFERROR(M23/$D23,"") | R23: ='AE Model'!$I$14 -> 3333.3333 | S23: =F23/R23 -> 0 | V23: ="Units Attain "&TEXT(H23,"0%")&" | % Exclusive "&TEXT(O23,"0%")&" | % to TSI "&TEXT(S23,"0%") -> Units Attain 0% | % Exclusive | % to TSI 0%
B24: Todd Myers | C24: AE | D24: =SUMIF($B$31:$B$45,$B24,$E$31:$E$45) -> 4 | E24: =SUMIF($B$31:$B$45,$B24,$F$31:$F$45) -> 311 | F24: =MIN(3*R24,SUMIF($B$31:$B$45,$B24,$H$31:$H$45)) -> 2976.27 | G24: ='AE Model'!$J$14 -> 383 | H24: =E24/G24 -> 0.81201044 | J24: =SUMIFS($E$31:$E$45,$D$31:$D$45,J$16,$B$31:$B$45,$B24) -> 0 | K24: =SUMIFS($E$31:$E$45,$D$31:$D$45,K$16,$B$31:$B$45,$B24) -> 4 | L24: =SUMIFS($E$31:$E$45,$D$31:$D$45,L$16,$B$31:$B$45,$B24) -> 0 | M24: =SUMIFS($E$31:$E$45,$D$31:$D$45,M$16,$B$31:$B$45,$B24) -> 0 | N24: =IFERROR(J24/$D24,"") -> 0 | O24: =IFERROR(K24/$D24,"") -> 1 | P24: =IFERROR(L24/$D24,"") -> 0 | Q24: =IFERROR(M24/$D24,"") -> 0 | R24: ='AE Model'!$I$14 -> 3333.3333 | S24: =F24/R24 -> 0.892881 | V24: ="Units Attain "&TEXT(H24,"0%")&" | % Exclusive "&TEXT(O24,"0%")&" | % to TSI "&TEXT(S24,"0%") -> Units Attain 81% | % Exclusive 100% | % to TSI 89%
B25: Morgan Carper | C25: Natl AE | D25: =SUMIF($B$31:$B$45,$B25,$E$31:$E$45) -> 4 | E25: =SUMIF($B$31:$B$45,$B25,$F$31:$F$45) -> 564 | F25: =MIN(3*R25,SUMIF($B$31:$B$45,$B25,$H$31:$H$45)) -> 6892.644 | G25: ='AE Model'!J15 -> 300 | H25: =E25/G25 -> 1.88 | J25: =SUMIFS($E$31:$E$45,$D$31:$D$45,J$16,$B$31:$B$45,$B25) -> 0 | K25: =SUMIFS($E$31:$E$45,$D$31:$D$45,K$16,$B$31:$B$45,$B25) -> 4 | L25: =SUMIFS($E$31:$E$45,$D$31:$D$45,L$16,$B$31:$B$45,$B25) -> 0 | M25: =SUMIFS($E$31:$E$45,$D$31:$D$45,M$16,$B$31:$B$45,$B25) -> 0 | N25: =IFERROR(J25/$D25,"") -> 0 | O25: =IFERROR(K25/$D25,"") -> 1 | P25: =IFERROR(L25/$D25,"") -> 0 | Q25: =IFERROR(M25/$D25,"") -> 0 | R25: ='AE Model'!$I$14 -> 3333.3333 | S25: =F25/R25 -> 2.0677932 | V25: ="Units Attain "&TEXT(H25,"0%")&" | % Exclusive "&TEXT(O25,"0%")&" | % to TSI "&TEXT(S25,"0%") -> Units Attain 188% | % Exclusive 100% | % to TSI 207%
B26: Total | D26: =SUM(D17:D25) -> 11 | E26: =SUM(E17:E25) -> 1157 | F26: =SUM(F17:F25) -> 11913.414 | G26: ='AE Model'!E4 -> 3353.4 | H26: =E26/G26 -> 0.34502296 | J26: =SUM(J17:J25) -> 1 | K26: =SUM(K17:K25) -> 10 | L26: =SUM(L17:L25) -> 0 | M26: =SUM(M17:M25) -> 0 | N26: =IFERROR(J26/$D26,"") -> 0.090909091 | O26: =IFERROR(K26/$D26,"") -> 0.90909091 | P26: =IFERROR(L26/$D26,"") -> 0 | Q26: =IFERROR(M26/$D26,"") -> 0
B28: Jason Herdrich | C28: Sr. Manager | D28: =D26 -> 11 | E28: =E26 -> 1157 | F28: =MIN(R28*2,H28*R28) -> 1725.1148 | G28: =G26 -> 3353.4 | H28: =E28/G28 -> 0.34502296 | J28: =J26 -> 1 | K28: =K26 -> 10 | L28: =L26 -> 0 | M28: =M26 -> 0 | N28: =N26 -> 0.090909091 | O28: =O26 -> 0.90909091 | P28: =P26 -> 0 | Q28: =Q26 -> 0 | R28: =60000/12 -> 5000 | S28: =F28/R28 -> 0.34502296
B30: [Account Manager] | C30: Role | D30: [Offer Type] | E30: Agreement Count | F30: Contracted Units | G30: Rate | H30: Commission
A31: =D31&" "&C31 -> Access AE | B31: Deanna Bethea | C31: AE | D31: Access | E31: =COUNTIFS($E$2:$E$12,$D31,$B$2:$B$12,$B31) -> 0 | F31: =SUMIFS(F$2:F$12,$B$2:$B$12,$B31,$E$2:$E$12,$D31) -> 0 | G31: =IFERROR(VLOOKUP(A31,AE_rates,4,FALSE),0) -> 6.09 | H31: =F31*G31 -> 0
A32: =D32&" "&C32 -> Exclusive AE | B32: Deanna Bethea | C32: AE | D32: Exclusive | E32: =COUNTIFS($E$2:$E$12,$D32,$B$2:$B$12,$B32) -> 1 | F32: =SUMIFS(F$2:F$12,$B$2:$B$12,$B32,$E$2:$E$12,$D32) -> 58 | G32: =IFERROR(VLOOKUP(A32,AE_rates,4,FALSE),0) -> 9.57 | H32: =F32*G32 -> 555.06
A33: =D33&" "&C33 -> Bulk AE | B33: Deanna Bethea | C33: AE | D33: Bulk | E33: =COUNTIFS($E$2:$E$12,$D33,$B$2:$B$12,$B33) -> 0 | F33: =SUMIFS(F$2:F$12,$B$2:$B$12,$B33,$E$2:$E$12,$D33) -> 0 | G33: =IFERROR(VLOOKUP(A33,AE_rates,4,FALSE),0) -> 12.18 | H33: =F33*G33 -> 0
A34: =D34&" "&C34 -> Access AE | B34: Guy Huntley | C34: AE | D34: Access | E34: =COUNTIFS($E$2:$E$12,$D34,$B$2:$B$12,$B34) -> 1 | F34: =SUMIFS(F$2:F$12,$B$2:$B$12,$B34,$E$2:$E$12,$D34) -> 188 | G34: =IFERROR(VLOOKUP(A34,AE_rates,4,FALSE),0) -> 6.09 | H34: =F34*G34 -> 1144.92
A35: =D35&" "&C35 -> Exclusive AE | B35: Guy Huntley | C35: AE | D35: Exclusive | E35: =COUNTIFS($E$2:$E$12,$D35,$B$2:$B$12,$B35) -> 0 | F35: =SUMIFS(F$2:F$12,$B$2:$B$12,$B35,$E$2:$E$12,$D35) -> 0 | G35: =IFERROR(VLOOKUP(A35,AE_rates,4,FALSE),0) -> 9.57 | H35: =F35*G35 -> 0
A36: =D36&" "&C36 -> Bulk AE | B36: Guy Huntley | C36: AE | D36: Bulk | E36: =COUNTIFS($E$2:$E$12,$D36,$B$2:$B$12,$B36) -> 0 | F36: =SUMIFS(F$2:F$12,$B$2:$B$12,$B36,$E$2:$E$12,$D36) -> 0 | G36: =IFERROR(VLOOKUP(A36,AE_rates,4,FALSE),0) -> 12.18 | H36: =F36*G36 -> 0
A37: =D37&" "&C37 -> Access AE | B37: Jennifer Raypole | C37: AE | D37: Access | E37: =COUNTIFS($E$2:$E$12,$D37,$B$2:$B$12,$B37) -> 0 | F37: =SUMIFS(F$2:F$12,$B$2:$B$12,$B37,$E$2:$E$12,$D37) -> 0 | G37: =IFERROR(VLOOKUP(A37,AE_rates,4,FALSE),0) -> 6.09 | H37: =F37*G37 -> 0
A38: =D38&" "&C38 -> Exclusive AE | B38: Jennifer Raypole | C38: AE | D38: Exclusive | E38: =COUNTIFS($E$2:$E$12,$D38,$B$2:$B$12,$B38) -> 1 | F38: =SUMIFS(F$2:F$12,$B$2:$B$12,$B38,$E$2:$E$12,$D38) -> 36 | G38: =IFERROR(VLOOKUP(A38,AE_rates,4,FALSE),0) -> 9.57 | H38: =F38*G38 -> 344.52
A39: =D39&" "&C39 -> Bulk AE | B39: Jennifer Raypole | C39: AE | D39: Bulk | E39: =COUNTIFS($E$2:$E$12,$D39,$B$2:$B$12,$B39) -> 0 | F39: =SUMIFS(F$2:F$12,$B$2:$B$12,$B39,$E$2:$E$12,$D39) -> 0 | G39: =IFERROR(VLOOKUP(A39,AE_rates,4,FALSE),0) -> 12.18 | H39: =F39*G39 -> 0
A40: =D40&" "&C40 -> Access Natl AE | B40: Morgan Carper | C40: Natl AE | D40: Access | E40: =COUNTIFS($E$2:$E$12,$D40,$B$2:$B$12,$B40) -> 0 | F40: =SUMIFS(F$2:F$12,$B$2:$B$12,$B40,$E$2:$E$12,$D40) -> 0 | G40: =IFERROR(VLOOKUP(A40,AE_rates,4,FALSE),0) -> 7.777 | H40: =F40*G40 -> 0
A41: =D41&" "&C41 -> Exclusive Natl AE | B41: Morgan Carper | C41: Natl AE | D41: Exclusive | E41: =COUNTIFS($E$2:$E$12,$D41,$B$2:$B$12,$B41) -> 4 | F41: =SUMIFS(F$2:F$12,$B$2:$B$12,$B41,$E$2:$E$12,$D41) -> 564 | G41: =IFERROR(VLOOKUP(A41,AE_rates,4,FALSE),0) -> 12.221 | H41: =F41*G41 -> 6892.644
A42: =D42&" "&C42 -> Bulk Natl AE | B42: Morgan Carper | C42: Natl AE | D42: Bulk | E42: =COUNTIFS($E$2:$E$12,$D42,$B$2:$B$12,$B42) -> 0 | F42: =SUMIFS(F$2:F$12,$B$2:$B$12,$B42,$E$2:$E$12,$D42) -> 0 | G42: =IFERROR(VLOOKUP(A42,AE_rates,4,FALSE),0) -> 15.554 | H42: =F42*G42 -> 0
... A45: =D45&" "&C45 -> Bulk AE | B45: Todd Myers | C45: AE | D45: Bulk | E45: =COUNTIFS($E$2:$E$12,$D45,$B$2:$B$12,$B45) -> 0 | F45: =SUMIFS(F$2:F$12,$B$2:$B$12,$B45,$E$2:$E$12,$D45) -> 0 | G45: =IFERROR(VLOOKUP(A45,AE_rates,4,FALSE),0) -> 12.18 | H45: =F45*G45 -> 0
E46: =SUM(E31:E45) -> 11 | F46: =SUM(F31:F45) -> 1157 | H46: =SUM(H31:H45) -> 11913.414

Sheet AE Jan Model
A1: Opportunity Name | B1: Opportunity Owner | C1: Offer Type | D1: Field Overbuild | E1: Total Units | F1: Contract Executed Date | G1: Close Month | H1: Stage | I1: Agreement
A2: GUND BREWERY LOFTS (AFFORDABLE)- | B2: Adam Sivertson | C2: BAA | D2: 1 | E2: 86 | F2: 1/29/2026, 12:00 PM | G2: 46023 | H2: Won | I2: =VLOOKUP(C2,AgreeMap,2,FALSE) -> Access
A3: Grand River Station Apartments | B3: Adam Sivertson | C3: BAA | D3: 1 | E3: 92 | F3: 1/29/2026, 12:00 PM | G3: 46023 | H3: Won | I3: =VLOOKUP(C3,AgreeMap,2,FALSE) -> Access | M3: [Account Manager] | N3: Role | O3: Jan Paid | P3: Jan Model | Q3: Jan Var | S3: Feb Model
A4: Castle Place-SMA | B4: Adam Sivertson | C4: Shared Marketing | D4: 0 | E4: 50 | F4: 1/30/2026, 12:00 PM | G4: 46023 | H4: Won | I4: =VLOOKUP(C4,AgreeMap,2,FALSE) -> Shared | M4: Adam Sivertson | N4: AE | O4: 3250 | P4: =H32 -> 1475.52 | Q4: =P4-O4 -> -1774.48 | S4: ='AE Feb Model'!F17 -> 0
A5: Alder Grove PH2 | B5: Amir Planes | C5: Exclusive Marketing | D5: 1 | E5: 117 | F5: 1/14/2026, 12:00 PM | G5: 46023 | H5: Won | I5: =VLOOKUP(C5,AgreeMap,2,FALSE) -> Exclusive | M5: Amir Planes | N5: AE | O5: 4000 | P5: =H33 -> 3562.65 | Q5: =P5-O5 -> -437.35 | S5: ='AE Feb Model'!F18 -> 0
A6: Brightman's Farm PH2 | B6: Amir Planes | C6: BEA Only | D6: 0 | E6: 162 | F6: 1/28/2026, 12:00 PM | G6: 46023 | H6: Won | I6: =VLOOKUP(C6,AgreeMap,2,FALSE) -> Access | M6: Constance James | N6: AE | O6: 3250 | P6: =H34 -> 995.28 | Q6: =P6-O6 -> -2254.72 | S6: ='AE Feb Model'!F19 -> 0
A7: Islands of Beaufort | B7: Amir Planes | C7: Shared Marketing | D7: 0 | E7: 186 | F7: 1/30/2026, 12:00 PM | G7: 46023 | H7: Won | I7: =VLOOKUP(C7,AgreeMap,2,FALSE) -> Shared | M7: Deanna Bethea | N7: AE | O7: 11050 | P7: =H35 -> 4494.42 | Q7: =P7-O7 -> -6555.58 | S7: ='AE Feb Model'!F20 -> 555.06
A8: Sandpiper Apartments | B8: Constance James | C8: Exclusive Marketing | D8: 1 | E8: 52 | F8: 1/9/2026, 12:00 PM | G8: 46023 | H8: Won | I8: =VLOOKUP(C8,AgreeMap,2,FALSE) -> Exclusive | M8: Guy Huntley | N8: AE | P8: =H36 -> 0 | Q8: =P8-O8 -> 0 | S8: ='AE Feb Model'!F21 -> 1144.92
A9: Glenbriar MHP | B9: Constance James | C9: Exclusive Marketing | D9: 1 | E9: 52 | F9: 1/15/2026, 12:00 PM | G9: 46023 | H9: Won | I9: =VLOOKUP(C9,AgreeMap,2,FALSE) -> Exclusive | M9: Jennifer Raypole | N9: AE | O9: 12300 | P9: =H37 -> 7669.42 | Q9: =P9-O9 -> -4630.58 | S9: ='AE Feb Model'!F22 -> 344.52
A10: Mission Cedar Village | B10: Deanna Bethea | C10: Shared Marketing | D10: 1 | E10: 77 | F10: 1/7/2026, 12:00 PM | G10: 46023 | H10: Won | I10: =VLOOKUP(C10,AgreeMap,2,FALSE) -> Shared | M10: Steve Norris | N10: AE | O10: 2500 | P10: =H38 -> 1315.44 | Q10: =P10-O10 -> -1184.56 | S10: ='AE Feb Model'!F23 -> 0
A11: Academy Village TH | B11: Deanna Bethea | C11: Bulk | D11: 1 | E11: 49 | F11: 1/7/2026, 12:00 PM | G11: 46023 | H11: Won | I11: =VLOOKUP(C11,AgreeMap,2,FALSE) -> Bulk | M11: Todd Myers | N11: AE | O11: 8000 | P11: =H39 -> 2490.81 | Q11: =P11-O11 -> -5509.19 | S11: ='AE Feb Model'!F24 -> 2976.27
A12: Harpers Meadows BSO | B12: Deanna Bethea | C12: BEA Only | D12: 1 | E12: 75 | F12: 1/9/2026, 12:00 PM | G12: 46023 | H12: Won | I12: =VLOOKUP(C12,AgreeMap,2,FALSE) -> Access | M12: Morgan Carper | N12: Natl AE | P12: =H40 -> 0 | Q12: =P12-O12 -> 0 | S12: ='AE Feb Model'!F25 -> 6892.644
A13: Lotus Ridge | B13: Deanna Bethea | C13: BAA | D13: 1 | E13: 177 | F13: 1/14/2026, 12:00 PM | G13: 46023 | H13: Won | I13: =VLOOKUP(C13,AgreeMap,2,FALSE) -> Access | M13: Total | O13: =SUM(O4:O12) -> 44350 | P13: =SUM(P4:P12) -> 22003.54 | Q13: =SUM(Q4:Q12) -> -22346.46 | S13: =SUM(S4:S12) -> 11913.414
A14: The Exchage at Vass MDU | B14: Deanna Bethea | C14: Bulk | D14: 1 | E14: 78 | F14: 1/28/2026, 12:00 PM | G14: 46023 | H14: Won | I14: =VLOOKUP(C14,AgreeMap,2,FALSE) -> Bulk
A15: Amberly Townhomes-BSO Gibsonville | B15: Deanna Bethea | C15: BAA | D15: 1 | E15: 133 | F15: 1/29/2026, 12:00 PM | G15: 46023 | H15: Won | I15: =VLOOKUP(C15,AgreeMap,2,FALSE) -> Access | M15: Sr. Manager | P15: =F43 -> 3740.9793 | S15: ='AE Feb Model'!F28 -> 1725.1148
A16: Hillview | B16: Jennifer Raypole | C16: Sole Provider | D16: 0 | E16: 91 | F16: 1/9/2026, 12:00 PM | G16: 46023 | H16: Won | I16: =VLOOKUP(C16,AgreeMap,2,FALSE) -> Exclusive
A17: The Luxe | B17: Jennifer Raypole | C17: Exclusive Marketing | D17: 1 | E17: 96 | F17: 1/26/2026, 12:00 PM | G17: 46023 | H17: Won | I17: =VLOOKUP(C17,AgreeMap,2,FALSE) -> Exclusive
A18: Oakwood Apartments | B18: Jennifer Raypole | C18: Exclusive Marketing | D18: 1 | E18: 240 | F18: 1/26/2026, 12:00 PM | G18: 46023 | H18: Won | I18: =VLOOKUP(C18,AgreeMap,2,FALSE) -> Exclusive
A19: The Valley at Great Hills Phase 4 | B19: Jennifer Raypole | C19: Exclusive Marketing | D19: 0 | E19: 171 | F19: 1/30/2026, 12:00 PM | G19: 46023 | H19: Won | I19: =VLOOKUP(C19,AgreeMap,2,FALSE) -> Exclusive
A20: Cedarvale MHC | B20: Jennifer Raypole | C20: BEA Only | D20: 1 | E20: 113 | F20: 1/28/2026, 12:00 PM | G20: 46023 | H20: Won | I20: =VLOOKUP(C20,AgreeMap,2,FALSE) -> Access
A21: The Reserve at Skyline Mountain Phase 2 | B21: Jennifer Raypole | C21: Exclusive Marketing | D21: 0 | E21: 27 | F21: 1/29/2026, 12:00 PM | G21: 46023 | H21: Won | I21: =VLOOKUP(C21,AgreeMap,2,FALSE) -> Exclusive
A22: Camden Ridge | B22: Steve Norris | C22: Bulk | D22: 1 | E22: 108 | F22: 1/14/2026, 12:00 PM | G22: 46023 | H22: Won | I22: =VLOOKUP(C22,AgreeMap,2,FALSE) -> Bulk
A23: COOPER STREET APARTMENTS | B23: Todd Myers | C23: Bulk | D23: 1 | E23: 60 | F23: 1/5/2026, 12:00 PM | G23: 46023 | H23: Won | I23: =VLOOKUP(C23,AgreeMap,2,FALSE) -> Bulk
A24: Fernandes Homes | B24: Todd Myers | C24: Exclusive Marketing | D24: 1 | E24: 35 | F24: 1/5/2026, 12:00 PM | G24: 46023 | H24: Won | I24: =VLOOKUP(C24,AgreeMap,2,FALSE) -> Exclusive
A25: Poplar Forest I - PP | B25: Todd Myers | C25: Shared Marketing | D25: 0 | E25: 72 | F25: 1/21/2026, 12:00 PM | G25: 46023 | H25: Won | I25: =VLOOKUP(C25,AgreeMap,2,FALSE) -> Shared
A26: Poplar Forest II - PP | B26: Todd Myers | C26: Shared Marketing | D26: 0 | E26: 66 | F26: 1/21/2026, 12:00 PM | G26: 46023 | H26: Won | I26: =VLOOKUP(C26,AgreeMap,2,FALSE) -> Shared
A27: Parc Crest at Poplar Forest - PP | B27: Todd Myers | C27: Shared Marketing | D27: 0 | E27: 44 | F27: 1/21/2026, 12:00 PM | G27: 46023 | H27: Won | I27: =VLOOKUP(C27,AgreeMap,2,FALSE) -> Shared
E28: =SUM(E2:E27) -> 2509
L30: Total Agreements | P30: Portfolio Contribution | T30: Contract Bonus
B31: [Account Manager] | C31: Role | D31: Tot Agreements | E31: Contracted Units | F31: Commission | G31: Contract Bonus | H31: Total Commission | I31: Units Target | J31: Units Attain | L31: Access | M31: Exclusive | N31: Shared | O31: Bulk | P31: Access | Q31: Exclusive | R31: Shared | S31: Bulk | T31: EMA+Bulk | U31: Bonus | W31: TSI | X31: % to TSI | Y31: Evaluation
B32: Adam Sivertson | C32: AE | D32: =SUMIF($B$46:$B$81,B32,$E$46:$E$81) -> 3 | E32: =SUMIF($B$46:$B$81,$B32,$F$46:$F$81) -> 228 | F32: =SUMIF($B$46:$B$81,$B32,$J$46:$J$81) -> 1475.52 | G32: =U32 -> 0 | H32: =MIN(W32*3,(F32+G32)) -> 1475.52 | I32: ='AE Model'!$J$14 -> 383 | J32: =E32/I32 -> 0.59530026 | L32: =SUMIFS($E$46:$E$81,$D$46:$D$81,L$31,$B$46:$B$81,$B32) -> 2 | M32: =SUMIFS($E$46:$E$81,$D$46:$D$81,M$31,$B$46:$B$81,$B32) -> 0 | N32: =SUMIFS($E$46:$E$81,$D$46:$D$81,N$31,$B$46:$B$81,$B32) -> 1 | O32: =SUMIFS($E$46:$E$81,$D$46:$D$81,O$31,$B$46:$B$81,$B32) -> 0 | P32: =IFERROR(L32/$D32,"") -> 0.66666667 | Q32: =IFERROR(M32/$D32,"") -> 0 | R32: =IFERROR(N32/$D32,"") -> 0.33333333 | S32: =IFERROR(O32/$D32,"") -> 0 | T32: =M32+O32 -> 0 | U32: =IF(T32>=5,1000,0) -> 0 | W32: ='AE Model'!$I$14 -> 3333.3333 | X32: =H32/W32 -> 0.442656 | Y32: ="Units Attain "&TEXT(J32,"0%")&" | % Exclusive "&TEXT(Q32,"0%")&" | % to TSI "&TEXT(X32,"0%") -> Units Attain 60% | % Exclusive 0% | % to TSI 44%
B33: Amir Planes | C33: AE | D33: =SUMIF($B$46:$B$81,B33,$E$46:$E$81) -> 3 | E33: =SUMIF($B$46:$B$81,$B33,$F$46:$F$81) -> 465 | F33: =SUMIF($B$46:$B$81,$B33,$J$46:$J$81) -> 3562.65 | G33: =U33 -> 0 | H33: =MIN(W33*3,(F33+G33)) -> 3562.65 | I33: ='AE Model'!$J$14 -> 383 | J33: =E33/I33 -> 1.2140992 | L33: =SUMIFS($E$46:$E$81,$D$46:$D$81,L$31,$B$46:$B$81,$B33) -> 1 | M33: =SUMIFS($E$46:$E$81,$D$46:$D$81,M$31,$B$46:$B$81,$B33) -> 1 | N33: =SUMIFS($E$46:$E$81,$D$46:$D$81,N$31,$B$46:$B$81,$B33) -> 1 | O33: =SUMIFS($E$46:$E$81,$D$46:$D$81,O$31,$B$46:$B$81,$B33) -> 0 | P33: =IFERROR(L33/$D33,"") -> 0.33333333 | Q33: =IFERROR(M33/$D33,"") -> 0.33333333 | R33: =IFERROR(N33/$D33,"") -> 0.33333333 | S33: =IFERROR(O33/$D33,"") -> 0 | T33: =M33+O33 -> 1 | U33: =IF(T33>=5,1000,0) -> 0 | W33: ='AE Model'!$I$14 -> 3333.3333 | X33: =H33/W33 -> 1.068795 | Y33: ="Units Attain "&TEXT(J33,"0%")&" | % Exclusive "&TEXT(Q33,"0%")&" | % to TSI "&TEXT(X33,"0%") -> Units Attain 121% | % Exclusive 33% | % to TSI 107%
B34: Constance James | C34: AE | D34: =SUMIF($B$46:$B$81,B34,$E$46:$E$81) -> 2 | E34: =SUMIF($B$46:$B$81,$B34,$F$46:$F$81) -> 104 | F34: =SUMIF($B$46:$B$81,$B34,$J$46:$J$81) -> 995.28 | G34: =U34 -> 0 | H34: =MIN(W34*3,(F34+G34)) -> 995.28 | I34: ='AE Model'!$J$14 -> 383 | J34: =E34/I34 -> 0.27154047 | L34: =SUMIFS($E$46:$E$81,$D$46:$D$81,L$31,$B$46:$B$81,$B34) -> 0 | M34: =SUMIFS($E$46:$E$81,$D$46:$D$81,M$31,$B$46:$B$81,$B34) -> 2 | N34: =SUMIFS($E$46:$E$81,$D$46:$D$81,N$31,$B$46:$B$81,$B34) -> 0 | O34: =SUMIFS($E$46:$E$81,$D$46:$D$81,O$31,$B$46:$B$81,$B34) -> 0 | P34: =IFERROR(L34/$D34,"") -> 0 | Q34: =IFERROR(M34/$D34,"") -> 1 | R34: =IFERROR(N34/$D34,"") -> 0 | S34: =IFERROR(O34/$D34,"") -> 0 | T34: =M34+O34 -> 2 | U34: =IF(T34>=5,1000,0) -> 0 | W34: ='AE Model'!$I$14 -> 3333.3333 | X34: =H34/W34 -> 0.298584 | Y34: ="Units Attain "&TEXT(J34,"0%")&" | % Exclusive "&TEXT(Q34,"0%")&" | % to TSI "&TEXT(X34,"0%") -> Units Attain 27% | % Exclusive 100% | % to TSI 30%
B35: Deanna Bethea | C35: AE | D35: =SUMIF($B$46:$B$81,B35,$E$46:$E$81) -> 6 | E35: =SUMIF($B$46:$B$81,$B35,$F$46:$F$81) -> 589 | F35: =SUMIF($B$46:$B$81,$B35,$J$46:$J$81) -> 4494.42 | G35: =U35 -> 0 | H35: =MIN(W35*3,(F35+G35)) -> 4494.42 | I35: ='AE Model'!$J$14 -> 383 | J35: =E35/I35 -> 1.537859 | L35: =SUMIFS($E$46:$E$81,$D$46:$D$81,L$31,$B$46:$B$81,$B35) -> 3 | M35: =SUMIFS($E$46:$E$81,$D$46:$D$81,M$31,$B$46:$B$81,$B35) -> 0 | N35: =SUMIFS($E$46:$E$81,$D$46:$D$81,N$31,$B$46:$B$81,$B35) -> 1 | O35: =SUMIFS($E$46:$E$81,$D$46:$D$81,O$31,$B$46:$B$81,$B35) -> 2 | P35: =IFERROR(L35/$D35,"") -> 0.5 | Q35: =IFERROR(M35/$D35,"") -> 0 | R35: =IFERROR(N35/$D35,"") -> 0.16666667 | S35: =IFERROR(O35/$D35,"") -> 0.33333333 | T35: =M35+O35 -> 2 | U35: =IF(T35>=5,1000,0) -> 0 | W35: ='AE Model'!$I$14 -> 3333.3333 | X35: =H35/W35 -> 1.348326 | Y35: ="Units Attain "&TEXT(J35,"0%")&" | % Exclusive "&TEXT(Q35,"0%")&" | % to TSI "&TEXT(X35,"0%") -> Units Attain 154% | % Exclusive 0% | % to TSI 135%
B36: Guy Huntley | C36: AE | D36: =SUMIF($B$46:$B$81,B36,$E$46:$E$81) -> 0 | E36: =SUMIF($B$46:$B$81,$B36,$F$46:$F$81) -> 0 | F36: =SUMIF($B$46:$B$81,$B36,$J$46:$J$81) -> 0 | G36: =U36 -> 0 | H36: =MIN(W36*3,(F36+G36)) -> 0 | I36: ='AE Model'!$J$14 -> 383 | J36: =E36/I36 -> 0 | L36: =SUMIFS($E$46:$E$81,$D$46:$D$81,L$31,$B$46:$B$81,$B36) -> 0 | M36: =SUMIFS($E$46:$E$81,$D$46:$D$81,M$31,$B$46:$B$81,$B36) -> 0 | N36: =SUMIFS($E$46:$E$81,$D$46:$D$81,N$31,$B$46:$B$81,$B36) -> 0 | O36: =SUMIFS($E$46:$E$81,$D$46:$D$81,O$31,$B$46:$B$81,$B36) -> 0 | P36: =IFERROR(L36/$D36,"") | Q36: =IFERROR(M36/$D36,"") | R36: =IFERROR(N36/$D36,"") | S36: =IFERROR(O36/$D36,"") | T36: =M36+O36 -> 0 | U36: =IF(T36>=5,1000,0) -> 0 | W36: ='AE Model'!$I$14 -> 3333.3333 | X36: =H36/W36 -> 0 | Y36: ="Units Attain "&TEXT(J36,"0%")&" | % Exclusive "&TEXT(Q36,"0%")&" | % to TSI "&TEXT(X36,"0%") -> Units Attain 0% | % Exclusive | % to TSI 0%
B37: Jennifer Raypole | C37: AE | D37: =SUMIF($B$46:$B$81,B37,$E$46:$E$81) -> 6 | E37: =SUMIF($B$46:$B$81,$B37,$F$46:$F$81) -> 738 | F37: =SUMIF($B$46:$B$81,$B37,$J$46:$J$81) -> 6669.42 | G37: =U37 -> 1000 | H37: =MIN(W37*3,(F37+G37)) -> 7669.42 | I37: ='AE Model'!$J$14 -> 383 | J37: =E37/I37 -> 1.926893 | L37: =SUMIFS($E$46:$E$81,$D$46:$D$81,L$31,$B$46:$B$81,$B37) -> 1 | M37: =SUMIFS($E$46:$E$81,$D$46:$D$81,M$31,$B$46:$B$81,$B37) -> 5 | N37: =SUMIFS($E$46:$E$81,$D$46:$D$81,N$31,$B$46:$B$81,$B37) -> 0 | O37: =SUMIFS($E$46:$E$81,$D$46:$D$81,O$31,$B$46:$B$81,$B37) -> 0 | P37: =IFERROR(L37/$D37,"") -> 0.16666667 | Q37: =IFERROR(M37/$D37,"") -> 0.83333333 | R37: =IFERROR(N37/$D37,"") -> 0 | S37: =IFERROR(O37/$D37,"") -> 0 | T37: =M37+O37 -> 5 | U37: =IF(T37>=5,1000,0) -> 1000 | W37: ='AE Model'!$I$14 -> 3333.3333 | X37: =H37/W37 -> 2.300826 | Y37: ="Units Attain "&TEXT(J37,"0%")&" | % Exclusive "&TEXT(Q37,"0%")&" | % to TSI "&TEXT(X37,"0%") -> Units Attain 193% | % Exclusive 83% | % to TSI 230%
B38: Steve Norris | C38: AE | D38: =SUMIF($B$46:$B$81,B38,$E$46:$E$81) -> 1 | E38: =SUMIF($B$46:$B$81,$B38,$F$46:$F$81) -> 108 | F38: =SUMIF($B$46:$B$81,$B38,$J$46:$J$81) -> 1315.44 | G38: =U38 -> 0 | H38: =MIN(W38*3,(F38+G38)) -> 1315.44 | I38: ='AE Model'!$J$14 -> 383 | J38: =E38/I38 -> 0.28198433 | L38: =SUMIFS($E$46:$E$81,$D$46:$D$81,L$31,$B$46:$B$81,$B38) -> 0 | M38: =SUMIFS($E$46:$E$81,$D$46:$D$81,M$31,$B$46:$B$81,$B38) -> 0 | N38: =SUMIFS($E$46:$E$81,$D$46:$D$81,N$31,$B$46:$B$81,$B38) -> 0 | O38: =SUMIFS($E$46:$E$81,$D$46:$D$81,O$31,$B$46:$B$81,$B38) -> 1 | P38: =IFERROR(L38/$D38,"") -> 0 | Q38: =IFERROR(M38/$D38,"") -> 0 | R38: =IFERROR(N38/$D38,"") -> 0 | S38: =IFERROR(O38/$D38,"") -> 1 | T38: =M38+O38 -> 1 | U38: =IF(T38>=5,1000,0) -> 0 | W38: ='AE Model'!$I$14 -> 3333.3333 | X38: =H38/W38 -> 0.394632 | Y38: ="Units Attain "&TEXT(J38,"0%")&" | % Exclusive "&TEXT(Q38,"0%")&" | % to TSI "&TEXT(X38,"0%") -> Units Attain 28% | % Exclusive 0% | % to TSI 39%
B39: Todd Myers | C39: AE | D39: =SUMIF($B$46:$B$81,B39,$E$46:$E$81) -> 5 | E39: =SUMIF($B$46:$B$81,$B39,$F$46:$F$81) -> 277 | F39: =SUMIF($B$46:$B$81,$B39,$J$46:$J$81) -> 2490.81 | G39: =U39 -> 0 | H39: =MIN(W39*3,(F39+G39)) -> 2490.81 | I39: ='AE Model'!$J$14 -> 383 | J39: =E39/I39 -> 0.7232376 | L39: =SUMIFS($E$46:$E$81,$D$46:$D$81,L$31,$B$46:$B$81,$B39) -> 0 | M39: =SUMIFS($E$46:$E$81,$D$46:$D$81,M$31,$B$46:$B$81,$B39) -> 1 | N39: =SUMIFS($E$46:$E$81,$D$46:$D$81,N$31,$B$46:$B$81,$B39) -> 3 | O39: =SUMIFS($E$46:$E$81,$D$46:$D$81,O$31,$B$46:$B$81,$B39) -> 1 | P39: =IFERROR(L39/$D39,"") -> 0 | Q39: =IFERROR(M39/$D39,"") -> 0.2 | R39: =IFERROR(N39/$D39,"") -> 0.6 | S39: =IFERROR(O39/$D39,"") -> 0.2 | T39: =M39+O39 -> 2 | U39: =IF(T39>=5,1000,0) -> 0 | W39: ='AE Model'!$I$14 -> 3333.3333 | X39: =H39/W39 -> 0.747243 | Y39: ="Units Attain "&TEXT(J39,"0%")&" | % Exclusive "&TEXT(Q39,"0%")&" | % to TSI "&TEXT(X39,"0%") -> Units Attain 72% | % Exclusive 20% | % to TSI 75%
B40: Morgan Carper | C40: Natl AE | D40: =SUMIF($B$46:$B$81,B40,$E$46:$E$81) -> 0 | E40: =SUMIF($B$46:$B$81,$B40,$F$46:$F$81) -> 0 | F40: =SUMIF($B$46:$B$81,$B40,$J$46:$J$81) -> 0 | G40: =U40 -> 0 | H40: =MIN(W40*3,(F40+G40)) -> 0 | I40: ='AE Model'!J15 -> 300 | J40: =E40/I40 -> 0 | L40: =SUMIFS($E$46:$E$81,$D$46:$D$81,L$31,$B$46:$B$81,$B40) -> 0 | M40: =SUMIFS($E$46:$E$81,$D$46:$D$81,M$31,$B$46:$B$81,$B40) -> 0 | N40: =SUMIFS($E$46:$E$81,$D$46:$D$81,N$31,$B$46:$B$81,$B40) -> 0 | O40: =SUMIFS($E$46:$E$81,$D$46:$D$81,O$31,$B$46:$B$81,$B40) -> 0 | P40: =IFERROR(L40/$D40,"") | Q40: =IFERROR(M40/$D40,"") | R40: =IFERROR(N40/$D40,"") | S40: =IFERROR(O40/$D40,"") | T40: =M40+O40 -> 0 | U40: =IF(T40>=5,1000,0) -> 0 | W40: ='AE Model'!$I$14 -> 3333.3333 | X40: =H40/W40 -> 0 | Y40: ="Units Attain "&TEXT(J40,"0%")&" | % Exclusive "&TEXT(Q40,"0%")&" | % to TSI "&TEXT(X40,"0%") -> Units Attain 0% | % Exclusive | % to TSI 0%
B41: Total | D41: =SUM(D32:D40) -> 26 | E41: =SUM(E32:E40) -> 2509 | F41: =SUM(F32:F40) -> 21003.54 | G41: =SUM(G32:G40) -> 1000 | H41: =SUM(H32:H40) -> 22003.54 | I41: ='AE Model'!D4 -> 3353.4 | J41: =E41/I41 -> 0.74819586 | L41: =SUM(L32:L40) -> 7 | M41: =SUM(M32:M40) -> 9 | N41: =SUM(N32:N40) -> 6 | O41: =SUM(O32:O40) -> 4 | P41: =IFERROR(L41/$D41,"") -> 0.26923077 | Q41: =IFERROR(M41/$D41,"") -> 0.34615385 | R41: =IFERROR(N41/$D41,"") -> 0.23076923 | S41: =IFERROR(O41/$D41,"") -> 0.15384615 | T41: =SUM(T32:T40) -> 13
B43: Jason Herdrich | C43: Sr. Manager | D43: =D41 -> 26 | E43: =E41 -> 2509 | F43: =MIN(W43*2,J43*W43) -> 3740.9793 | I43: =I41 -> 3353.4 | J43: =E43/I43 -> 0.74819586 | L43: =L41 -> 7 | M43: =M41 -> 9 | N43: =N41 -> 6 | O43: =O41 -> 4 | P43: =P41 -> 0.26923077 | Q43: =Q41 -> 0.34615385 | R43: =R41 -> 0.23076923 | S43: =S41 -> 0.15384615 | W43: =60000/12 -> 5000 | X43: =I43/W43 -> 0.67068
B45: [Account Manager] | C45: Role | D45: [Offer Type] | E45: Agreement Count | F45: Contracted Units | I45: Rate | J45: Commission
A46: =D46&" "&C46 -> Access AE | B46: Adam Sivertson | C46: AE | D46: Access | E46: =COUNTIFS($I$2:$I$27,$D46,$B$2:$B$27,$B46) -> 2 | F46: =SUMIFS(E$2:E$27,$B$2:$B$27,$B46,$I$2:$I$27,$D46) -> 178 | I46: =IFERROR(VLOOKUP(A46,AE_rates,4,FALSE),0) -> 6.09 | J46: =F46*I46 -> 1084.02
A47: =D47&" "&C47 -> Shared AE | B47: Adam Sivertson | C47: AE | D47: Shared | E47: =COUNTIFS($I$2:$I$27,$D47,$B$2:$B$27,$B47) -> 1 | F47: =SUMIFS(E$2:E$27,$B$2:$B$27,$B47,$I$2:$I$27,$D47) -> 50 | I47: =IFERROR(VLOOKUP(A47,AE_rates,4,FALSE),0) -> 7.83 | J47: =F47*I47 -> 391.5
A48: =D48&" "&C48 -> Exclusive AE | B48: Adam Sivertson | C48: AE | D48: Exclusive | E48: =COUNTIFS($I$2:$I$27,$D48,$B$2:$B$27,$B48) -> 0 | F48: =SUMIFS(E$2:E$27,$B$2:$B$27,$B48,$I$2:$I$27,$D48) -> 0 | I48: =IFERROR(VLOOKUP(A48,AE_rates,4,FALSE),0) -> 9.57 | J48: =F48*I48 -> 0
A49: =D49&" "&C49 -> Bulk AE | B49: Adam Sivertson | C49: AE | D49: Bulk | E49: =COUNTIFS($I$2:$I$27,$D49,$B$2:$B$27,$B49) -> 0 | F49: =SUMIFS(E$2:E$27,$B$2:$B$27,$B49,$I$2:$I$27,$D49) -> 0 | I49: =IFERROR(VLOOKUP(A49,AE_rates,4,FALSE),0) -> 12.18 | J49: =F49*I49 -> 0
A50: =D50&" "&C50 -> Access AE | B50: Amir Planes | C50: AE | D50: Access | E50: =COUNTIFS($I$2:$I$27,$D50,$B$2:$B$27,$B50) -> 1 | F50: =SUMIFS(E$2:E$27,$B$2:$B$27,$B50,$I$2:$I$27,$D50) -> 162 | I50: =IFERROR(VLOOKUP(A50,AE_rates,4,FALSE),0) -> 6.09 | J50: =F50*I50 -> 986.58
A51: =D51&" "&C51 -> Shared AE | B51: Amir Planes | C51: AE | D51: Shared | E51: =COUNTIFS($I$2:$I$27,$D51,$B$2:$B$27,$B51) -> 1 | F51: =SUMIFS(E$2:E$27,$B$2:$B$27,$B51,$I$2:$I$27,$D51) -> 186 | I51: =IFERROR(VLOOKUP(A51,AE_rates,4,FALSE),0) -> 7.83 | J51: =F51*I51 -> 1456.38
A52: =D52&" "&C52 -> Exclusive AE | B52: Amir Planes | C52: AE | D52: Exclusive | E52: =COUNTIFS($I$2:$I$27,$D52,$B$2:$B$27,$B52) -> 1 | F52: =SUMIFS(E$2:E$27,$B$2:$B$27,$B52,$I$2:$I$27,$D52) -> 117 | I52: =IFERROR(VLOOKUP(A52,AE_rates,4,FALSE),0) -> 9.57 | J52: =F52*I52 -> 1119.69
A53: =D53&" "&C53 -> Bulk AE | B53: Amir Planes | C53: AE | D53: Bulk | E53: =COUNTIFS($I$2:$I$27,$D53,$B$2:$B$27,$B53) -> 0 | F53: =SUMIFS(E$2:E$27,$B$2:$B$27,$B53,$I$2:$I$27,$D53) -> 0 | I53: =IFERROR(VLOOKUP(A53,AE_rates,4,FALSE),0) -> 12.18 | J53: =F53*I53 -> 0
A54: =D54&" "&C54 -> Access AE | B54: Constance James | C54: AE | D54: Access | E54: =COUNTIFS($I$2:$I$27,$D54,$B$2:$B$27,$B54) -> 0 | F54: =SUMIFS(E$2:E$27,$B$2:$B$27,$B54,$I$2:$I$27,$D54) -> 0 | I54: =IFERROR(VLOOKUP(A54,AE_rates,4,FALSE),0) -> 6.09 | J54: =F54*I54 -> 0
A55: =D55&" "&C55 -> Shared AE | B55: Constance James | C55: AE | D55: Shared | E55: =COUNTIFS($I$2:$I$27,$D55,$B$2:$B$27,$B55) -> 0 | F55: =SUMIFS(E$2:E$27,$B$2:$B$27,$B55,$I$2:$I$27,$D55) -> 0 | I55: =IFERROR(VLOOKUP(A55,AE_rates,4,FALSE),0) -> 7.83 | J55: =F55*I55 -> 0
A56: =D56&" "&C56 -> Exclusive AE | B56: Constance James | C56: AE | D56: Exclusive | E56: =COUNTIFS($I$2:$I$27,$D56,$B$2:$B$27,$B56) -> 2 | F56: =SUMIFS(E$2:E$27,$B$2:$B$27,$B56,$I$2:$I$27,$D56) -> 104 | I56: =IFERROR(VLOOKUP(A56,AE_rates,4,FALSE),0) -> 9.57 | J56: =F56*I56 -> 995.28
A57: =D57&" "&C57 -> Bulk AE | B57: Constance James | C57: AE | D57: Bulk | E57: =COUNTIFS($I$2:$I$27,$D57,$B$2:$B$27,$B57) -> 0 | F57: =SUMIFS(E$2:E$27,$B$2:$B$27,$B57,$I$2:$I$27,$D57) -> 0 | I57: =IFERROR(VLOOKUP(A57,AE_rates,4,FALSE),0) -> 12.18 | J57: =F57*I57 -> 0
... A81: =D81&" "&C81 -> Bulk Natl AE | B81: Morgan Carper | C81: Natl AE | D81: Bulk | E81: =COUNTIFS($I$2:$I$27,$D81,$B$2:$B$27,$B81) -> 0 | F81: =SUMIFS(E$2:E$27,$B$2:$B$27,$B81,$I$2:$I$27,$D81) -> 0 | I81: =IFERROR(VLOOKUP(A81,AE_rates,4,FALSE),0) -> 15.554 | J81: =F81*I81 -> 0
E82: =SUM(E46:E81) -> 26 | F82: =SUM(F46:F81) -> 2509 | J82: =SUM(J46:J81) -> 21003.54

Sheet TSR Model
B2: TSR Targets | C2: Role | E2: Targets | F2: JAN | G2: FEB | H2: MAR | I2: APR | J2: MAY | K2: JUN | L2: JUL | M2: AUG | N2: SEP | O2: OCT | P2: NOV | Q2: DEC
B3: TSR Portfolio Penetration | C3: Sr. Mgr, Dir, Sr. Dir | D3: > % new month over % prior month (baseline) -- % Change
B4: TSR Rep Portfolio Penetration | C4: TSR | D4: > % new month over % prior month (baseline) -- % Change
E6: Headcount | F6: JAN | G6: FEB | H6: MAR | I6: APR | J6: MAY | K6: JUN | L6: JUL | M6: AUG | N6: SEP | O6: OCT | P6: NOV | Q6: DEC
B7: TSR Units Sold (Team) | C7: Sr. Mgr, Dir, Sr. Dir | D7: > sum of targets of the team | F7: =($E8*F8)+($E9*F9) -> 1200 | G7: =($E8*G8)+($E9*G9) -> 1200 | H7: =($E8*H8)+($E9*H9) -> 1200 | I7: =($E8*I8)+($E9*I9) -> 1520 | J7: =($E8*J8)+($E9*J9) -> 1520 | K7: =($E8*K8)+($E9*K9) -> 1520 | L7: =($E8*L8)+($E9*L9) -> 1885 | M7: =($E8*M8)+($E9*M9) -> 1885 | ... Q7: =($E8*Q8)+($E9*Q9) -> 1275
B8: TSR Units Sold (TSR MDU) | C8: TSR (MDU) | E8: 3 | F8: 300 | G8: 300 | H8: 300 | I8: 390 | J8: 390 | K8: 390 | L8: 495 | M8: 495 | N8: 495 | O8: 325 | P8: 325 | Q8: 325
B9: TSR Units Sold (TSR SFU) | C9: TSR (SFU) | E9: 1 | F9: 300 | G9: 300 | H9: 300 | I9: 350 | J9: 350 | K9: 350 | L9: 400 | M9: 400 | N9: 400 | O9: 300 | P9: 300 | Q9: 300
C11: Components & Weight | G11: Thresholds
B12: Roles | C12: Penetration | D12: Units Sold | E12: Penetration | F12: Units Sold | G12: Min | H12: Max
B13: TSR (MDU) | C13: 50% TSI | D13: 50% TSI | E13: % MoM Change | F13: % Attain to Target | G13: None | H13: 200% of TSI
B14: TSR (SFU) | C14: 50% TSI | D14: 50% TSI | E14: % MoM Change | F14: % Attain to Target | G14: None | H14: 200% of TSI | I14: new hire TBD
B15: Sr Mgr | C15: 50% TSI | D15: 50% TSI | E15: % MoM Change | F15: % Attain to Target | G15: None | H15: 200% of TSI
B17: Eligible Transactions for Earnings
B18: TSR | C18: Penetration report and Units sold report to be provided monthly
B19: Sr Mgr | C19: Aggregation of TSR team +SFU transactions for both Penetration and Units Sold

Sheet TSR Sales Feb Sample
A1: [TSR] | B1: [ORDER #] | C1: [SRVC_TYP] | D1: [STATE] | E1: [ORDER DATE] | F1: [Wirecenter Name] | G1: [Wirecenter ID]
A2: Freddy Morales | B2: AL1100047194 | C2: fQF Internet | D2: AL | E2: 2026-02-02T00:00:00 | F2: PELL CITY | G2: PLCYALXA
A3: Freddy Morales | B3: AL1100047243 | C3: Fiber Internet | D3: AL | E3: 2026-02-02T00:00:00 | F3: FOLEY | G3: FOLYALXA
A4: Freddy Morales | B4: AL1100047252 | C4: Fiber Internet | D4: AL | E4: 2026-02-02T00:00:00 | F4: ROBERTSDALE | G4: RBDLALXA
A5: Freddy Morales | B5: AL1100047265 | C5: Fiber Internet | D5: AL | E5: 2026-02-02T00:00:00 | F5: FOLEY | G5: FOLYALXA
A6: Freddy Morales | B6: AL1100047309 | C6: Fiber Internet | D6: AL | E6: 2026-02-03T00:00:00 | F6: FOLEY | G6: FOLYALXA
A7: Freddy Morales | B7: AL1100047312 | C7: Fiber Internet | D7: AL | E7: 2026-02-03T00:00:00 | F7: FOLEY | G7: FOLYALXA
A8: Freddy Morales | B8: AL1100047333 | C8: Fiber Internet | D8: AL | E8: 2026-02-03T00:00:00 | F8: FOLEY | G8: FOLYALXA
A9: Freddy Morales | B9: AL1100047397 | C9: Fiber Internet | D9: AL | E9: 2026-02-04T00:00:00 | F9: FOLEY | G9: FOLYALXA
A10: Freddy Morales | B10: AL1100047421 | C10: Fiber Internet | D10: AL | E10: 2026-02-04T00:00:00 | F10: FOLEY | G10: FOLYALXA
A11: Freddy Morales | B11: AL1100047460 | C11: Fiber Internet | D11: AL | E11: 2026-02-05T00:00:00 | F11: ORANGE BEACH | G11: ORBHALXA
A12: Freddy Morales | B12: AL1100047473 | C12: Fiber Internet | D12: AL | E12: 2026-02-05T00:00:00 | F12: ORANGE BEACH | G12: ORBHALXA
... A186: Freddy Morales | B186: WI1100019385 | C186: Fiber Internet | D186: WI | E186: 2026-02-07T00:00:00 | F186: PINE RIVER | G186: PYSPWIXA
A187: Freddy Morales | B187: WI1100019390 | C187: DSL | D187: WI | E187: 2026-02-07T00:00:00
A188: Freddy Morales | B188: WI1100019392 | C188: Instant Internet | D188: WI | E188: 2026-02-07T00:00:00 | F188: ONALASKA | G188: LCRSWIXA
A189: Freddy Morales | B189: WI1100019393 | C189: Instant Internet | D189: WI | E189: 2026-02-07T00:00:00 | F189: LA CROSSE | G189: LCRSWIXB
A190: Freddy Morales | B190: WI1100019402 | C190: Instant Internet | D190: WI | E190: 2026-02-09T00:00:00 | F190: TOMAH | G190: TOMAWIXA
A191: Freddy Morales | B191: WI1100019428 | C191: Instant Internet | D191: WI | E191: 2026-02-10T00:00:00 | F191: LA CROSSE | G191: LCRSWIXC
A192: Freddy Morales | B192: WI1100019451 | C192: Fiber Internet | D192: WI | E192: 2026-02-10T00:00:00 | F192: PLATTEVILLE | G192: PTVLWIXA
A193: Freddy Morales | B193: WI1100019465 | C193: Instant Internet | D193: WI | E193: 2026-02-11T00:00:00 | F193: HOLMEN | G193: LCRSWIXA
A194: Freddy Morales | B194: WI1100019468 | C194: Instant Internet | D194: WI | E194: 2026-02-11T00:00:00 | F194: ONALASKA | G194: LCRSWIXA
A195: Freddy Morales | B195: WI1100019484 | C195: Fiber Internet | D195: WI | E195: 2026-02-11T00:00:00 | F195: PLATTEVILLE | G195: PTVLWIXA
A196: Freddy Morales | B196: WI1100019487 | C196: fQF Internet | D196: WI | E196: 2026-02-11T00:00:00 | F196: LA CROSSE | G196: LCRSWIXC
A197: Freddy Morales | B197: WI1100019510 | C197: Instant Internet | D197: WI | E197: 2026-02-13T00:00:00 | F197: HOLMEN | G197: HLMNWIXA
A198: Freddy Morales | B198: WI1100019512 | C198: Fiber Internet | D198: WI | E198: 2026-02-13T00:00:00 | F198: PLATTEVILLE | G198: PTVLWIXA
A199: Freddy Morales | B199: WI1100019515 | C199: Instant Internet | D199: WI | E199: 2026-02-13T00:00:00 | F199: ONALASKA | G199: LCRSWIXA
... A290: Joseph Buckles | B290: NC1100172195 | C290: Instant Internet | D290: NC | E290: 2026-02-17T00:00:00 | F290: NEW BERN | G290: NWBRNCXA
A291: Joseph Buckles | B291: NC1100172251 | C291: DSL | D291: NC | E291: 2026-02-17T00:00:00
A292: Joseph Buckles | B292: NC1100172259 | C292: Instant Internet+Value Added Services | D292: NC | E292: 2026-02-17T00:00:00 | F292: PITTSBORO | G292: PTBONCXA
A293: Joseph Buckles | B293: NC1100172266 | C293: Instant Internet | D293: NC | E293: 2026-02-17T00:00:00 | F293: NEW BERN | G293: NWBRNCXA
A294: Joseph Buckles | B294: NC1100172315 | C294: Instant Internet | D294: NC | E294: 2026-02-17T00:00:00 | F294: FUQUAY VARINA | G294: FQVRNCXA
A295: Joseph Buckles | B295: NC1100172586 | C295: Instant Internet | D295: NC | E295: 2026-02-18T00:00:00 | F295: NEW BERN | G295: NWBRNCXA
A296: Joseph Buckles | B296: NC1100172602 | C296: Fiber Internet | D296: NC | E296: 2026-02-18T00:00:00 | F296: GREENVILLE | G296: GNVLNCXB
A297: Joseph Buckles | B297: NC1100172639 | C297: fQF Internet | D297: NC | E297: 2026-02-18T00:00:00 | F297: SMITHFIELD | G297: SMFDNCXA
A298: Joseph Buckles | B298: NC1100172789 | C298: Instant Internet | D298: NC | E298: 2026-02-18T00:00:00 | F298: TARBORO | G298: TRBONCXA
A299: Joseph Buckles | B299: NC1100172919 | C299: Fiber Internet | D299: NC | E299: 2026-02-19T00:00:00 | F299: SMITHFIELD | G299: SMFDNCXA
A300: Joseph Buckles | B300: OH1100067342 | C300: BrightSpeed Internet | D300: OH | E300: 2026-02-01T00:00:00 | F300: LORAIN | G300: LORNOHXC
A301: Joseph Buckles | B301: OH1100067501 | C301: BrightSpeed Internet | D301: OH | E301: 2026-02-03T00:00:00 | F301: LORAIN | G301: LORNOHXC
A302: Joseph Buckles | B302: OH1100067504 | C302: BrightSpeed Internet | D302: OH | E302: 2026-02-03T00:00:00 | F302: LORAIN | G302: LORNOHXC
A303: Joseph Buckles | B303: OH1100067555 | C303: BrightSpeed Internet+Value Added Services | D303: OH | E303: 2026-02-03T00:00:00 | F303: LORAIN | G303: LORNOHXC
... A373: Karsten Freeman | B373: MO1100079665 | C373: Instant Internet | D373: MO | E373: 2026-02-01T00:00:00 | F373: COLUMBIA | G373: CLMAMOXA
A374: Karsten Freeman | B374: MO1100079671 | C374: DSL | D374: MO | E374: 2026-02-01T00:00:00
A375: Karsten Freeman | B375: MO1100079673 | C375: Instant Internet | D375: MO | E375: 2026-02-01T00:00:00 | F375: LAKE SAINT LOUIS | G375: DRDNMOXA
A376: Karsten Freeman | B376: MO1100079679 | C376: Fiber Internet | D376: MO | E376: 2026-02-01T00:00:00 | F376: JEFFERSON CITY | G376: JFCYMOXA
A377: Karsten Freeman | B377: MO1100079684 | C377: Instant Internet | D377: MO | E377: 2026-02-02T00:00:00 | F377: SAINT PETERS | G377: STPRMOXA
A378: Karsten Freeman | B378: MO1100079708 | C378: Fiber Internet | D378: MO | E378: 2026-02-02T00:00:00 | F378: COLUMBIA | G378: CLMAMOXA
A379: Karsten Freeman | B379: MO1100079718 | C379: Fiber Internet | D379: MO | E379: 2026-02-02T00:00:00 | F379: COLUMBIA | G379: CLMAMOXA
A380: Karsten Freeman | B380: MO1100079721 | C380: Instant Internet | D380: MO | E380: 2026-02-02T00:00:00 | F380: COLUMBIA | G380: CLMAMOXA
A381: Karsten Freeman | B381: MO1100079724 | C381: fQF Internet | D381: MO | E381: 2026-02-02T00:00:00 | F381: MOSCOW MILLS | G381: MSMLMOXA
A382: Karsten Freeman | B382: MO1100079727 | C382: Fiber Internet | D382: MO | E382: 2026-02-02T00:00:00 | F382: JEFFERSON CITY | G382: JFCYMOXA
A383: Karsten Freeman | B383: MO1100079742 | C383: Fiber Internet | D383: MO | E383: 2026-02-02T00:00:00 | F383: COLUMBIA | G383: CLMAMOXB
A384: Karsten Freeman | B384: MO1100079768 | C384: Fiber Internet | D384: MO | E384: 2026-02-02T00:00:00 | F384: SPRINGFIELD | G384: SPFIMOAH
A385: Karsten Freeman | B385: MO1100079810 | C385: fQF Internet | D385: MO | E385: 2026-02-03T00:00:00 | F385: SAINT ROBERT | G385: STRBMOXA
A386: Karsten Freeman | B386: MO1100079842 | C386: Fiber Internet | D386: MO | E386: 2026-02-03T00:00:00 | F386: COLUMBIA | G386: CLMAMOXB
... A407: Karsten Freeman | B407: MO1100080131 | C407: Fiber Internet | D407: MO | E407: 2026-02-06T00:00:00 | F407: COLUMBIA | G407: CLMAMOXB
A408: Karsten Freeman | B408: MO1100080155 | C408: DSL | D408: MO | E408: 2026-02-06T00:00:00
A409: Karsten Freeman | B409: MO1100080157 | C409: Fiber Internet | D409: MO | E409: 2026-02-06T00:00:00 | F409: SPRINGFIELD | G409: SPFIMOAH
A410: Karsten Freeman | B410: MO1100080164 | C410: Instant Internet | D410: MO | E410: 2026-02-06T00:00:00 | F410: MOSCOW MILLS | G410: MSMLMOXA
A411: Karsten Freeman | B411: MO1100080176 | C411: Fiber Internet | D411: MO | E411: 2026-02-06T00:00:00 | F411: JEFFERSON CITY | G411: JFCYMOXA
A412: Karsten Freeman | B412: MO1100080186 | C412: fQF Internet | D412: MO | E412: 2026-02-07T00:00:00 | F412: BRANSON | G412: BASNMOXA
A413: Karsten Freeman | B413: MO1100080199 | C413: Fiber Internet | D413: MO | E413: 2026-02-07T00:00:00 | F413: SPRINGFIELD | G413: SPFIMOAH
A414: Karsten Freeman | B414: MO1100080205 | C414: Fiber Internet | D414: MO | E414: 2026-02-07T00:00:00 | F414: COLUMBIA | G414: CLMAMOXA
A415: Karsten Freeman | B415: MO1100080206 | C415: Instant Internet | D415: MO | E415: 2026-02-07T00:00:00 | F415: O FALLON | G415: DRDNMOXA
A416: Karsten Freeman | B416: MO1100080210 | C416: Fiber Internet | D416: MO | E416: 2026-02-07T00:00:00 | F416: COLUMBIA | G416: CLMAMOXA
A417: Karsten Freeman | B417: MO1100080215 | C417: Instant Internet | D417: MO | E417: 2026-02-07T00:00:00 | F417: BRANSON | G417: BASNMOXA
A418: Karsten Freeman | B418: MO1100080222 | C418: Instant Internet | D418: MO | E418: 2026-02-07T00:00:00 | F418: BRANSON | G418: BASNMOXA
A419: Karsten Freeman | B419: MO1100080224 | C419: Instant Internet | D419: MO | E419: 2026-02-07T00:00:00 | F419: LAKE SAINT LOUIS | G419: DRDNMOXA
A420: Karsten Freeman | B420: MO1100080226 | C420: Instant Internet | D420: MO | E420: 2026-02-07T00:00:00 | F420: BRANSON | G420: BASNMOXA
... A424: Karsten Freeman | B424: MO1100080271 | C424: Fiber Internet | D424: MO | E424: 2026-02-09T00:00:00 | F424: SPRINGFIELD | G424: SPFFMOEI
A425: Karsten Freeman | B425: MO1100080273 | C425: DSL | D425: MO | E425: 2026-02-09T00:00:00
A426: Karsten Freeman | B426: MO1100080281 | C426: Fiber Internet | D426: MO | E426: 2026-02-09T00:00:00 | F426: SPRINGFIELD | G426: SPFFMOEI
A427: Karsten Freeman | B427: MO1100080286 | C427: Fiber Internet | D427: MO | E427: 2026-02-09T00:00:00 | F427: COLUMBIA | G427: CLMAMOXA
A428: Karsten Freeman | B428: MO1100080296 | C428: Fiber Internet | D428: MO | E428: 2026-02-09T00:00:00 | F428: JEFFERSON CITY | G428: JFCYMOXA
A429: Karsten Freeman | B429: MO1100080326 | C429: Fiber Internet | D429: MO | E429: 2026-02-09T00:00:00 | F429: COLUMBIA | G429: CLMAMOXA
A430: Karsten Freeman | B430: MO1100080331 | C430: Instant Internet | D430: MO | E430: 2026-02-09T00:00:00 | F430: BRANSON | G430: BASNMOXA
A431: Karsten Freeman | B431: MO1100080447 | C431: Fiber Internet | D431: MO | E431: 2026-02-10T00:00:00 | F431: COLUMBIA | G431: CLMAMOXA
A432: Karsten Freeman | B432: MO1100080538 | C432: Fiber Internet | D432: MO | E432: 2026-02-10T00:00:00 | F432: COLUMBIA | G432: CLMAMOXA
A433: Karsten Freeman | B433: MO1100080553 | C433: Instant Internet | D433: MO | E433: 2026-02-10T00:00:00 | F433: BRANSON | G433: BASNMOXA
A434: Karsten Freeman | B434: MO1100080555 | C434: Instant Internet | D434: MO | E434: 2026-02-11T00:00:00 | F434: LAKE SAINT LOUIS | G434: DRDNMOXA
A435: Karsten Freeman | B435: MO1100080583 | C435: Instant Internet | D435: MO | E435: 2026-02-11T00:00:00 | F435: LAKE SAINT LOUIS | G435: DRDNMOXA
A436: Karsten Freeman | B436: MO1100080624 | C436: Instant Internet | D436: MO | E436: 2026-02-11T00:00:00 | F436: SAINT PETERS | G436: STPRMOXA
A437: Karsten Freeman | B437: MO1100080654 | C437: Fiber Internet | D437: MO | E437: 2026-02-11T00:00:00 | F437: SPRINGFIELD | G437: SPFIMOAH
... A447: Karsten Freeman | B447: MO1100080851 | C447: Fiber Internet | D447: MO | E447: 2026-02-12T00:00:00 | F447: COLUMBIA | G447: CLMAMOXB
A448: Karsten Freeman | B448: MO1100080852 | C448: DSL | D448: MO | E448: 2026-02-12T00:00:00
A449: Karsten Freeman | B449: MO1100080873 | C449: fQF Internet | D449: MO | E449: 2026-02-12T00:00:00 | F449: WAYNESVILLE | G449: WYVLMOXA
A450: Karsten Freeman | B450: MO1100080921 | C450: fQF Internet | D450: MO | E450: 2026-02-13T00:00:00 | F450: WARRENSBURG | G450: WRBGMOXA
A451: Karsten Freeman | B451: MO1100080937 | C451: Fiber Internet | D451: MO | E451: 2026-02-13T00:00:00 | F451: JEFFERSON CITY | G451: JFCYMOXA
A452: Karsten Freeman | B452: MO1100080975 | C452: Fiber Internet | D452: MO | E452: 2026-02-13T00:00:00 | F452: COLUMBIA | G452: CLMAMOXA
A453: Karsten Freeman | B453: MO1100080977 | C453: Instant Internet | D453: MO | E453: 2026-02-13T00:00:00 | F453: WENTZVILLE | G453: WNVLMOXA
A454: Karsten Freeman | B454: MO1100080979 | C454: Fiber Internet | D454: MO | E454: 2026-02-13T00:00:00 | F454: COLUMBIA | G454: CLMAMOXA
A455: Karsten Freeman | B455: MO1100080993 | C455: Fiber Internet | D455: MO | E455: 2026-02-13T00:00:00 | F455: JEFFERSON CITY | G455: JFCYMOXA
A456: Karsten Freeman | B456: MO1100081022 | C456: Fiber Internet | D456: MO | E456: 2026-02-13T00:00:00 | F456: COLUMBIA | G456: CLMAMOXA
A457: Karsten Freeman | B457: MO1100081041 | C457: Fiber Internet | D457: MO | E457: 2026-02-14T00:00:00 | F457: COLUMBIA | G457: CLMAMOXA
A458: Karsten Freeman | B458: MO1100081043 | C458: Instant Internet | D458: MO | E458: 2026-02-14T00:00:00 | F458: O FALLON | G458: DRDNMOXA
A459: Karsten Freeman | B459: MO1100081070 | C459: Fiber Internet | D459: MO | E459: 2026-02-14T00:00:00 | F459: SPRINGFIELD | G459: SPFIMOAH
A460: Karsten Freeman | B460: MO1100081072 | C460: Fiber Internet | D460: MO | E460: 2026-02-14T00:00:00 | F460: COLUMBIA | G460: CLMAMOXA
... A531: Norman Mundy | B531: AL1100048370 | C531: fQF Internet | D531: AL | E531: 2026-02-15T00:00:00 | F531: ROBERTSDALE | G531: RBDLALXA
A532: Norman Mundy | B532: AL1100048372 | C532: DSL | D532: AL | E532: 2026-02-15T00:00:00
A533: Norman Mundy | B533: AL1100048381 | C533: fQF Internet | D533: AL | E533: 2026-02-15T00:00:00 | F533: ROBERTSDALE | G533: RBDLALXA
A534: Norman Mundy | B534: AL1100048391 | C534: fQF Internet | D534: AL | E534: 2026-02-15T00:00:00 | F534: ROBERTSDALE | G534: RBDLALXA
...

Sheet TSR Sales Feb Model
A1: [TSR] | B1: [ORDER #] | C1: [SRVC_TYP] | D1: [STATE] | E1: [ORDER DATE] | H1: TSR Name | I1: WireCenter Name | J1: WireCenter ID
A2: 6d5fe13cc3956210c73cdda77d0131a5 | B2: AL1100047194 | C2: fQF Internet | D2: AL | E2: 2026-02-02T00:00:00
A3: 6d5fe13cc3956210c73cdda77d0131a5 | B3: AL1100047243 | C3: Fiber Internet | D3: AL | E3: 2026-02-02T00:00:00
A4: 6d5fe13cc3956210c73cdda77d0131a5 | B4: AL1100047252 | C4: Fiber Internet | D4: AL | E4: 2026-02-02T00:00:00 | H4: Row Labels | I4: Count of [ORDER #]
A5: 6d5fe13cc3956210c73cdda77d0131a5 | B5: AL1100047265 | C5: Fiber Internet | D5: AL | E5: 2026-02-02T00:00:00 | H5: 6d5fe13cc3956210c73cdda77d0131a5 | I5: 181
A6: 6d5fe13cc3956210c73cdda77d0131a5 | B6: AL1100047309 | C6: Fiber Internet | D6: AL | E6: 2026-02-03T00:00:00 | H6: Joseph Buckles | I6: 140
A7: 6d5fe13cc3956210c73cdda77d0131a5 | B7: AL1100047312 | C7: Fiber Internet | D7: AL | E7: 2026-02-03T00:00:00 | H7: Karsten Freeman | I7: 129
A8: 6d5fe13cc3956210c73cdda77d0131a5 | B8: AL1100047333 | C8: Fiber Internet | D8: AL | E8: 2026-02-03T00:00:00 | H8: Norman Mundy | I8: 274
A9: 6d5fe13cc3956210c73cdda77d0131a5 | B9: AL1100047397 | C9: Fiber Internet | D9: AL | E9: 2026-02-04T00:00:00 | H9: Grand Total | I9: 724
A10: 6d5fe13cc3956210c73cdda77d0131a5 | B10: AL1100047421 | C10: Fiber Internet | D10: AL | E10: 2026-02-04T00:00:00
A11: 6d5fe13cc3956210c73cdda77d0131a5 | B11: AL1100047460 | C11: Fiber Internet | D11: AL | E11: 2026-02-05T00:00:00
A12: 6d5fe13cc3956210c73cdda77d0131a5 | B12: AL1100047473 | C12: Fiber Internet | D12: AL | E12: 2026-02-05T00:00:00
A13: 6d5fe13cc3956210c73cdda77d0131a5 | B13: AL1100047503 | C13: Fiber Internet | D13: AL | E13: 2026-02-05T00:00:00
A14: 6d5fe13cc3956210c73cdda77d0131a5 | B14: AL1100047512 | C14: Fiber Internet | D14: AL | E14: 2026-02-05T00:00:00
A15: 6d5fe13cc3956210c73cdda77d0131a5 | B15: AL1100047524 | C15: Fiber Internet | D15: AL | E15: 2026-02-05T00:00:00
A16: 6d5fe13cc3956210c73cdda77d0131a5 | B16: AL1100047585 | C16: Fiber Internet | D16: AL | E16: 2026-02-06T00:00:00 | I16: Sales | J16: Target | K16: % Attain | M16: Jan Pen | N16: Feb Pen | O16: Change | S16: Jan Sales | T16: Target | U16: % Attain
A17: 6d5fe13cc3956210c73cdda77d0131a5 | B17: AL1100047623 | C17: Fiber Internet | D17: AL | E17: 2026-02-06T00:00:00 | G17: TSR MDU | H17: Freddy Morales | I17: 181 | J17: 300 | K17: =I17/J17 -> 0.60333333 | M17: ='TSR Pen sample'!X3 -> 0.36779789 | N17: ='TSR Pen sample'!Y3 -> 0.37056116 | O17: =N17/M17 -> 1.007513 | S17: 289 | T17: 300 | U17: =S17/T17 -> 0.96333333
A18: 6d5fe13cc3956210c73cdda77d0131a5 | B18: AL1100047654 | C18: Fiber Internet | D18: AL | E18: 2026-02-07T00:00:00 | G18: TSR MDU | H18: Joseph Buckles | I18: 140 | J18: 300 | K18: =I18/J18 -> 0.46666667 | M18: ='TSR Pen sample'!X4 -> 0.29690977 | N18: ='TSR Pen sample'!Y4 -> 0.2970401 | O18: =N18/M18 -> 1.000439 | S18: 209 | T18: 300 | U18: =S18/T18 -> 0.69666667
A19: 6d5fe13cc3956210c73cdda77d0131a5 | B19: AL1100047797 | C19: Fiber Internet | D19: AL | E19: 2026-02-09T00:00:00 | G19: TSR MDU | H19: Karsten Freeman | I19: 129 | J19: 300 | K19: =I19/J19 -> 0.43 | M19: ='TSR Pen sample'!X5 -> 0.41986121 | N19: ='TSR Pen sample'!Y5 -> 0.41663896 | O19: =N19/M19 -> 0.99232542 | S19: 267 | T19: 300 | U19: =S19/T19 -> 0.89
A20: 6d5fe13cc3956210c73cdda77d0131a5 | B20: AL1100047831 | C20: Fiber Internet | D20: AL | E20: 2026-02-09T00:00:00 | G20: TSR SFU | H20: Name TBD | I20: 274 | J20: 300 | K20: =I20/J20 -> 0.91333333 | M20: ='TSR Pen sample'!X6 -> 0.3087164 | N20: ='TSR Pen sample'!Y6 -> 0.30485468 | O20: =N20/M20 -> 0.98749105 | S20: 450 | T20: 300 | U20: =S20/T20 -> 1.5
A21: 6d5fe13cc3956210c73cdda77d0131a5 | B21: AL1100047851 | C21: Fiber Internet | D21: AL | E21: 2026-02-10T00:00:00 | I21: =SUM(I17:I20) -> 724 | J21: =SUM(J17:J20) -> 1200 | K21: =I21/J21 -> 0.60333333 | S21: =SUM(S17:S20) -> 1215 | T21: =SUM(T17:T20) -> 1200 | U21: =S21/T21 -> 1.0125
A22: 6d5fe13cc3956210c73cdda77d0131a5 | B22: AL1100047879 | C22: Fiber Internet | D22: AL | E22: 2026-02-10T00:00:00
A23: 6d5fe13cc3956210c73cdda77d0131a5 | B23: AL1100047957 | C23: Fiber Internet | D23: AL | E23: 2026-02-11T00:00:00 | G23: Sr. Mgr | H23: Norman Mundy | I23: =I21 -> 724 | J23: =J21 -> 1200 | K23: =K21 -> 0.60333333 | M23: ='TSR Pen sample'!X7 -> 0.33489239 | N23: ='TSR Pen sample'!Y7 -> 0.33287581 | O23: =N23/M23 -> 0.99397842 | S23: =S21 -> 1215 | T23: =T21 -> 1200 | U23: =U21 -> 1.0125
A24: 6d5fe13cc3956210c73cdda77d0131a5 | B24: AL1100047967 | C24: Fiber Internet | D24: AL | E24: 2026-02-11T00:00:00
A25: 6d5fe13cc3956210c73cdda77d0131a5 | B25: AL1100047993 | C25: Fiber Internet | D25: AL | E25: 2026-02-11T00:00:00
A26: 6d5fe13cc3956210c73cdda77d0131a5 | B26: AL1100048001 | C26: Fiber Internet | D26: AL | E26: 2026-02-11T00:00:00 | J26: 0.5 | M26: 0.5
A27: 6d5fe13cc3956210c73cdda77d0131a5 | B27: AL1100048064 | C27: Fiber Internet | D27: AL | E27: 2026-02-12T00:00:00 | G27: FEBRUARY MODEL | I27: TSI | J27: TSI Sales | K27: % Attain | L27: Sales Comm | M27: TSI Pen | N27: Pen Change | O27: Pen Comm | P27: Tot Comm | Q27: % to TSI | S27: Jan Paid | T27: Jan Model | U27: Jan Var
A28: 6d5fe13cc3956210c73cdda77d0131a5 | B28: AL1100048084 | C28: Fiber Internet | D28: AL | E28: 2026-02-12T00:00:00 | G28: TSR MDU | H28: Freddy Morales | I28: =30000/12 -> 2500 | J28: =I28*J$26 -> 1250 | K28: =K17 -> 0.60333333 | L28: =J28*K28 -> 754.16667 | M28: =I28*M$26 -> 1250 | N28: =O17 -> 1.007513 | O28: =M28*N28 -> 1259.3913 | P28: =L28+O28 -> 2013.5579 | Q28: =P28/I28 -> 0.80542317 | S28: 2435.8333 | T28: =P40 -> 2574.7755 | U28: =T28-S28 -> 138.94213
A29: 6d5fe13cc3956210c73cdda77d0131a5 | B29: AL1100048090 | C29: Fiber Internet | D29: AL | E29: 2026-02-12T00:00:00 | G29: TSR MDU | H29: Joseph Buckles | I29: =30000/12 -> 2500 | J29: =I29*J$26 -> 1250 | K29: =K18 -> 0.46666667 | L29: =J29*K29 -> 583.33333 | M29: =I29*M$26 -> 1250 | N29: =O18 -> 1.000439 | O29: =M29*N29 -> 1250.5487 | P29: =L29+O29 -> 1833.8821 | Q29: =P29/I29 -> 0.73355283 | S29: 1969.1667 | T29: =P41 -> 2151.7366 | U29: =T29-S29 -> 182.56995
A30: 6d5fe13cc3956210c73cdda77d0131a5 | B30: AL1100048148 | C30: Fiber Internet | D30: AL | E30: 2026-02-12T00:00:00 | G30: TSR MDU | H30: Karsten Freeman | I30: =30000/12 -> 2500 | J30: =I30*J$26 -> 1250 | K30: =K19 -> 0.43 | L30: =J30*K30 -> 537.5 | M30: =I30*M$26 -> 1250 | N30: =O19 -> 0.99232542 | O30: =M30*N30 -> 1240.4068 | P30: =L30+O30 -> 1777.9068 | Q30: =P30/I30 -> 0.71116271 | S30: 2307.5 | T30: =P42 -> 2370.672 | U30: =T30-S30 -> 63.172022
A31: 6d5fe13cc3956210c73cdda77d0131a5 | B31: AL1100048221 | C31: Fiber Internet | D31: AL | E31: 2026-02-13T00:00:00 | G31: TSR SFU | H31: Name TBD | I31: =30000/12 -> 2500 | J31: =I31*J$26 -> 1250 | K31: =K20 -> 0.91333333 | L31: =J31*K31 -> 1141.6667 | M31: =I31*M$26 -> 1250 | N31: =O20 -> 0.98749105 | O31: =M31*N31 -> 1234.3638 | P31: =L31+O31 -> 2376.0305 | Q31: =P31/I31 -> 0.95041219 | T31: =P43 -> 3166.1596 | U31: =T31-S31 -> 3166.1596
A32: 6d5fe13cc3956210c73cdda77d0131a5 | B32: AL1100048225 | C32: fQF Internet | D32: AL | E32: 2026-02-13T00:00:00 | L32: =SUM(L28:L31) -> 3016.6667 | O32: =SUM(O28:O31) -> 4984.7106 | P32: =SUM(P28:P31) -> 8001.3773 | S32: =SUM(S28:S31) -> 6712.5 | T32: =SUM(T28:T31) -> 10263.344 | U32: =SUM(U28:U31) -> 3550.8437
A33: 6d5fe13cc3956210c73cdda77d0131a5 | B33: AL1100048241 | C33: Fiber Internet | D33: AL | E33: 2026-02-13T00:00:00
A34: 6d5fe13cc3956210c73cdda77d0131a5 | B34: AL1100048251 | C34: fQF Internet | D34: AL | E34: 2026-02-13T00:00:00 | G34: Sr. Mgr | H34: Norman Mundy | I34: =50000/12 -> 4166.6667 | J34: =I34*J$26 -> 2083.3333 | K34: =K23 -> 0.60333333 | L34: =J34*K34 -> 1256.9444 | M34: =I34*M$26 -> 2083.3333 | N34: =O23 -> 0.99397842 | O34: =M34*N34 -> 2070.7884 | P34: =L34+O34 -> 3327.7328 | Q34: =P34/I34 -> 0.79865588 | S34: 4284.8333 | T34: =P46 -> 4270.2033 | U34: =T34-S34 -> -14.630016
A35: 6d5fe13cc3956210c73cdda77d0131a5 | B35: AL1100048258 | C35: Fiber Internet | D35: AL | E35: 2026-02-13T00:00:00
A36: 6d5fe13cc3956210c73cdda77d0131a5 | B36: AL1100048296 | C36: Fiber Internet | D36: AL | E36: 2026-02-14T00:00:00
A37: 6d5fe13cc3956210c73cdda77d0131a5 | B37: AL1100048399 | C37: Fiber Internet | D37: AL | E37: 2026-02-16T00:00:00
A38: 6d5fe13cc3956210c73cdda77d0131a5 | B38: AL1100048419 | C38: Fiber Internet | D38: AL | E38: 2026-02-16T00:00:00 | J38: 0.5 | M38: 0.5
A39: 6d5fe13cc3956210c73cdda77d0131a5 | B39: AL1100048450 | C39: Fiber Internet | D39: AL | E39: 2026-02-16T00:00:00 | G39: JANUARY MODEL | I39: TSI | J39: TSI Sales | K39: % Attain | L39: Sales Comm | M39: TSI Pen | N39: Pen Change | O39: Pen Comm | P39: Tot Comm | Q39: % to TSI
A40: 6d5fe13cc3956210c73cdda77d0131a5 | B40: AL1100048476 | C40: Fiber Internet | D40: AL | E40: 2026-02-16T00:00:00 | G40: TSR MDU | H40: Freddy Morales | I40: =30000/12 -> 2500 | J40: =I40*J$26 -> 1250 | K40: =U17 -> 0.96333333 | L40: =J40*K40 -> 1204.1667 | M40: =I40*M$26 -> 1250 | N40: ='TSR Pen sample'!X3/'TSR Pen sample'!W3 -> 1.096487 | O40: =M40*N40 -> 1370.6088 | P40: =L40+O40 -> 2574.7755 | Q40: =P40/I40 -> 1.0299102
A41: 6d5fe13cc3956210c73cdda77d0131a5 | B41: AL1100048502 | C41: Fiber Internet | D41: AL | E41: 2026-02-17T00:00:00 | G41: TSR MDU | H41: Joseph Buckles | I41: =30000/12 -> 2500 | J41: =I41*J$26 -> 1250 | K41: =U18 -> 0.69666667 | L41: =J41*K41 -> 870.83333 | M41: =I41*M$26 -> 1250 | N41: ='TSR Pen sample'!X4/'TSR Pen sample'!W4 -> 1.0247226 | O41: =M41*N41 -> 1280.9033 | P41: =L41+O41 -> 2151.7366 | Q41: =P41/I41 -> 0.86069465
A42: 6d5fe13cc3956210c73cdda77d0131a5 | B42: AR1100035136 | C42: Fiber Internet | D42: AR | E42: 2026-02-03T00:00:00 | G42: TSR MDU | H42: Karsten Freeman | I42: =30000/12 -> 2500 | J42: =I42*J$26 -> 1250 | K42: =U19 -> 0.89 | L42: =J42*K42 -> 1112.5 | M42: =I42*M$26 -> 1250 | N42: ='TSR Pen sample'!X5/'TSR Pen sample'!W5 -> 1.0065376 | O42: =M42*N42 -> 1258.172 | P42: =L42+O42 -> 2370.672 | Q42: =P42/I42 -> 0.94826881
A43: 6d5fe13cc3956210c73cdda77d0131a5 | B43: AR1100035191 | C43: Fiber Internet | D43: AR | E43: 2026-02-04T00:00:00 | G43: TSR SFU | H43: Name TBD | I43: =30000/12 -> 2500 | J43: =I43*J$26 -> 1250 | K43: =U20 -> 1.5 | L43: =J43*K43 -> 1875 | M43: =I43*M$26 -> 1250 | N43: ='TSR Pen sample'!X6/'TSR Pen sample'!W6 -> 1.0329277 | O43: =M43*N43 -> 1291.1596 | P43: =L43+O43 -> 3166.1596 | Q43: =P43/I43 -> 1.2664639
A44: 6d5fe13cc3956210c73cdda77d0131a5 | B44: AR1100035358 | C44: Fiber Internet | D44: AR | E44: 2026-02-06T00:00:00 | L44: =SUM(L40:L43) -> 5062.5 | O44: =SUM(O40:O43) -> 5200.8437 | P44: =SUM(P40:P43) -> 10263.344
A45: 6d5fe13cc3956210c73cdda77d0131a5 | B45: AR1100035376 | C45: Fiber Internet | D45: AR | E45: 2026-02-06T00:00:00
A46: 6d5fe13cc3956210c73cdda77d0131a5 | B46: AR1100035387 | C46: Fiber Internet | D46: AR | E46: 2026-02-06T00:00:00 | G46: Sr. Mgr | H46: Norman Mundy | I46: =50000/12 -> 4166.6667 | J46: =I46*J$26 -> 2083.3333 | K46: =U23 -> 1.0125 | L46: =J46*K46 -> 2109.375 | M46: =I46*M$26 -> 2083.3333 | N46: ='TSR Pen sample'!X7/'TSR Pen sample'!W7 -> 1.0371976 | O46: =M46*N46 -> 2160.8283 | P46: =L46+O46 -> 4270.2033 | Q46: =P46/I46 -> 1.0248488
A47: 6d5fe13cc3956210c73cdda77d0131a5 | B47: AR1100035737 | C47: Fiber Internet | D47: AR | E47: 2026-02-12T00:00:00
A48: 6d5fe13cc3956210c73cdda77d0131a5 | B48: AR1100035738 | C48: Fiber Internet | D48: AR | E48: 2026-02-12T00:00:00
A49: 6d5fe13cc3956210c73cdda77d0131a5 | B49: AR1100035743 | C49: Fiber Internet | D49: AR | E49: 2026-02-12T00:00:00
A50: 6d5fe13cc3956210c73cdda77d0131a5 | B50: AR1100035883 | C50: Instant Internet | D50: AR | E50: 2026-02-14T00:00:00
A51: 6d5fe13cc3956210c73cdda77d0131a5 | B51: NJ1100008114 | C51: Fiber Internet | D51: NJ | E51: 2026-02-10T00:00:00
A52: 6d5fe13cc3956210c73cdda77d0131a5 | B52: NJ1100008135 | C52: fQF Internet | D52: NJ | E52: 2026-02-12T00:00:00
A53: 6d5fe13cc3956210c73cdda77d0131a5 | B53: TX1100043765 | C53: Instant Internet+Value Added Services | D53: TX | E53: 2026-02-01T00:00:00
A54: 6d5fe13cc3956210c73cdda77d0131a5 | B54: TX1100043773 | C54: Fiber Internet | D54: TX | E54: 2026-02-01T00:00:00
A55: 6d5fe13cc3956210c73cdda77d0131a5 | B55: TX1100043783 | C55: Fiber Internet+Value Added Services | D55: TX | E55: 2026-02-01T00:00:00
A56: 6d5fe13cc3956210c73cdda77d0131a5 | B56: TX1100043810 | C56: Fiber Internet | D56: TX | E56: 2026-02-01T00:00:00
A57: 6d5fe13cc3956210c73cdda77d0131a5 | B57: TX1100043819 | C57: Fiber Internet | D57: TX | E57: 2026-02-01T00:00:00
A58: 6d5fe13cc3956210c73cdda77d0131a5 | B58: TX1100043852 | C58: fQF Internet | D58: TX | E58: 2026-02-02T00:00:00
... A725: Norman Mundy | B725: VA1100025474 | C725: Fiber Internet | D725: VA | E725: 2026-02-15T00:00:00

Sheet TSR Pen sample
A1: MMM-YY | B1: 45352 | C1: 45383 | D1: 45413 | E1: 45444 | F1: 45474 | G1: 45505 | H1: 45536 | I1: 45566 | J1: 45597 | K1: 45627 | L1: 45658 | M1: 45689 | N1: 45717 | O1: 45748 | P1: 45778 | Q1: 45809 | R1: 45839 | S1: 45870 | T1: 45901 | U1: 45931 | V1: 45962 | W1: 45992 | X1: 46023 | Y1: 46054
A2: TSR | B2: Penetration | C2: Penetration | D2: Penetration | E2: Penetration | F2: Penetration | G2: Penetration | H2: Penetration | I2: Penetration | J2: Penetration | K2: Penetration | L2: Penetration | M2: Penetration | N2: Penetration | O2: Penetration | P2: Penetration | Q2: Penetration | R2: Penetration | S2: Penetration | T2: Penetration | U2: Penetration | V2: Penetration | W2: Penetration | X2: Penetration | Y2: Penetration
A3: Freddy Morales | B3: 0.24350688 | C3: 0.27533436 | D3: 0.24530947 | E3: 0.25040545 | F3: 0.2140825 | G3: 0.25073659 | H3: 0.2633833 | I3: 0.2619574 | J3: 0.22209076 | K3: 0.22414227 | L3: 0.22081778 | M3: 0.2266261 | N3: 0.22920844 | O3: 0.23267682 | P3: 0.23573702 | Q3: 0.23825402 | R3: 0.29516223 | S3: 0.31546017 | T3: 0.32354434 | U3: 0.32757272 | V3: 0.32985137 | W3: 0.33543296 | X3: 0.36779789 | Y3: 0.37056116
A4: Joseph Buckles | B4: 0.19722927 | C4: 0.32000658 | D4: 0.26213347 | E4: 0.27872611 | F4: 0.24361229 | G4: 0.26253257 | H4: 0.27373484 | I4: 0.27103825 | J4: 0.24910364 | K4: 0.25168248 | L4: 0.2586673 | M4: 0.26549708 | N4: 0.26613564 | O4: 0.26661306 | P4: 0.27969069 | Q4: 0.2862201 | R4: 0.29898947 | S4: 0.3029898 | T4: 0.2892281 | U4: 0.28571429 | V4: 0.2908814 | W4: 0.28974647 | X4: 0.29690977 | Y4: 0.2970401
A5: Karsten Freeman | B5: 0.37071283 | C5: 0.39719203 | D5: 0.39898038 | E5: 0.40644307 | F5: 0.35784496 | G5: 0.34359646 | H5: 0.34932119 | I5: 0.34987093 | J5: 0.37377987 | K5: 0.37511361 | L5: 0.37714521 | M5: 0.38074644 | N5: 0.38485329 | O5: 0.38827233 | P5: 0.38693621 | Q5: 0.38966958 | R5: 0.39847439 | S5: 0.41084093 | T5: 0.41291486 | U5: 0.41400684 | V5: 0.42077202 | W5: 0.41713415 | X5: 0.41986121 | Y5: 0.41663896
A6: Norman Mundy | B6: 0.27001672 | C6: 0.27627754 | D6: 0.283861 | E6: 0.29143872 | F6: 0.28220505 | G6: 0.28024039 | H6: 0.28529013 | I6: 0.29261316 | J6: 0.2453834 | K6: 0.25439251 | L6: 0.2884487 | M6: 0.28664518 | N6: 0.27983009 | O6: 0.27376566 | P6: 0.27447751 | Q6: 0.2701242 | R6: 0.31033149 | S6: 0.31054427 | T6: 0.31041087 | U6: 0.30397384 | V6: 0.29681689 | W6: 0.29887512 | X6: 0.3087164 | Y6: 0.30485468
A7: Total | B7: 0.2704824 | C7: 0.3064113 | D7: 0.29456908 | E7: 0.30328076 | F7: 0.27623545 | G7: 0.28571171 | H7: 0.29365769 | I7: 0.29595088 | J7: 0.26542244 | K7: 0.27059949 | L7: 0.28692349 | M7: 0.28926617 | N7: 0.28714721 | O7: 0.28553844 | P7: 0.28872796 | Q7: 0.28847487 | R7: 0.32119537 | S7: 0.32751967 | T7: 0.32630901 | U7: 0.32301908 | V7: 0.32162908 | W7: 0.32288196 | X7: 0.33489239 | Y7: 0.33287581
A9: Applied filters: MMM-YY is on or after Feb-23 ParamMeasure is Penetration TSR is Freddy Morales, Joseph Buckles, Karsten Freeman, or Norman Mundy Qual_mo 2/18/2024 - 2/17/2026 ParamDimension is TSR ParameterMeasure_RS is Penetration MMM-YY 2/18/2024 - 2/17/2026 PRPTY_ID_FILTER is not (Blank) Account_class is Consumer
A12: TSR Name | B12: Date | C12: Penetration
A13: Freddy Morales | B13: 45352 | C13: 0.24350688
A14: Freddy Morales | B14: 45383 | C14: 0.27533436
A15: Freddy Morales | B15: 45413 | C15: 0.24530947
A16: Freddy Morales | B16: 45444 | C16: 0.25040545
A17: Freddy Morales | B17: 45474 | C17: 0.2140825
A18: Freddy Morales | B18: 45505 | C18: 0.25073659
A19: Freddy Morales | B19: 45536 | C19: 0.2633833
A20: Freddy Morales | B20: 45566 | C20: 0.2619574
A21: Freddy Morales | B21: 45597 | C21: 0.22209076
A22: Freddy Morales | B22: 45627 | C22: 0.22414227
A23: Freddy Morales | B23: 45658 | C23: 0.22081778
A24: Freddy Morales | B24: 45689 | C24: 0.2266261
... A36: Freddy Morales | B36: 46054 | C36: 0.37056116

Sheet Dir Model
C2: Jan | D2: Feb | E2: Mar | F2: Apr | G2: May | H2: Jun | I2: Jul | J2: Aug | K2: Sep | L2: Oct | M2: Nov | N2: Dec | O2: Total
B3: AE: Units Contracted (Budget) | C3: ='AE Model'!D9 -> 3726 | D3: ='AE Model'!E9 -> 3726 | E3: ='AE Model'!F9 -> 3726 | F3: ='AE Model'!G9 -> 3726 | G3: ='AE Model'!H9 -> 3726 | H3: ='AE Model'!I9 -> 3726 | I3: ='AE Model'!J9 -> 3726 | J3: ='AE Model'!K9 -> 3726 | ... N3: ='AE Model'!O9 -> 3726 | O3: =SUM(C3:N3) -> 44712
B4: TSR: Penetration | C4: > % new month over % prior month (baseline) -- % Change
B5: TSR: Units Sold | C5: ='TSR Model'!F7 -> 1200 | D5: ='TSR Model'!G7 -> 1200 | E5: ='TSR Model'!H7 -> 1200 | F5: ='TSR Model'!I7 -> 1520 | G5: ='TSR Model'!J7 -> 1520 | H5: ='TSR Model'!K7 -> 1520 | I5: ='TSR Model'!L7 -> 1885 | J5: ='TSR Model'!M7 -> 1885 | ... N5: ='TSR Model'!Q7 -> 1275 | O5: =SUM(C5:N5) -> 17640
D7: Components & Weight | I7: Thresholds
B8: Roles | C8: Units Contracted | D8: Penetration | E8: Units Sold | F8: Units Contracted | G8: Penetration | H8: Units Sold | I8: Min | J8: Max
B9: Dir, Sr Dir | C9: 50% TSI | D9: 25% TSI | E9: 25% TSI | F9: % Attain to Target | G9: % MoM Change | H9: % Attain to Target | I9: None | J9: 200% of TSI
B10: Data Source and Aggregation is the same as defined in the AE and TSR Plans
B12: Dir TSI | C12: =70000/12 -> 5833.3333
C13: =C12*0.5 -> 2916.6667 | D13: =C12*0.25 -> 1458.3333 | E13: =C12*0.25 -> 1458.3333
C15: JAN MODEL
C16: Target | D16: Attain | E16: Attain % | F16: TSI | G16: Commission | H16: % to TSI
B17: AE: Units Contracted | C17: ='AE Model'!D3 -> 3726 | D17: ='AE Jan Model'!E41 -> 2509 | E17: =D17/C17 -> 0.67337627 | F17: =C13 -> 2916.6667 | G17: =E17*F17 -> 1964.0141
B18: TSR: Penetration | C18: ='TSR Pen sample'!W7 -> 0.32288196 | D18: ='TSR Pen sample'!X7 -> 0.33489239 | E18: =D18/C18 -> 1.0371976 | F18: =D13 -> 1458.3333 | G18: =E18*F18 -> 1512.5798
B19: TSR: Units Sold | C19: =C5 -> 1200 | D19: ='TSR Sales Feb Model'!S23 -> 1215 | E19: =D19/C19 -> 1.0125 | F19: =E13 -> 1458.3333 | G19: =E19*F19 -> 1476.5625
F20: =SUM(F17:F19) -> 5833.3333 | G20: =SUM(G17:G19) -> 4953.1565 | H20: =G20/F20 -> 0.84911254
E21: Paid in Jan | G21: 5328.8236
E22: Var | G22: =G20-G21 -> -375.66711
C24: FEB MODEL
C25: Target | D25: Attain | E25: Attain % | F25: TSI | G25: Commission | H25: % to TSI
B26: AE: Units Contracted | C26: =D3 -> 3726 | D26: ='AE Feb Model'!E28 -> 1157 | E26: =D26/C26 -> 0.31052067 | F26: =F17 -> 2916.6667 | G26: =E26*F26 -> 905.68527
B27: TSR: Penetration | C27: ='TSR Pen sample'!X7 -> 0.33489239 | D27: ='TSR Pen sample'!Y7 -> 0.33287581 | E27: =D27/C27 -> 0.99397842 | F27: =F18 -> 1458.3333 | G27: =E27*F27 -> 1449.5519
B28: TSR: Units Sold | C28: =D5 -> 1200 | D28: ='TSR Sales Feb Model'!I23 -> 724 | E28: =D28/C28 -> 0.60333333 | F28: =F19 -> 1458.3333 | G28: =E28*F28 -> 879.86111
F29: =SUM(F26:F28) -> 5833.3333 | G29: =SUM(G26:G28) -> 3235.0983 | H29: =G29/F29 -> 0.55458827

Sheet Payroll
A1: Employee Name | B1: LOB | C1: Position | D1: 45658 | E1: 45689 | F1: 45717 | G1: 45748 | H1: 45778 | I1: 45809 | J1: 45839 | K1: 45870 | L1: 45901 | M1: 45931 | N1: 45962 | O1: 45992 | P1: 46023
A2: Todd Myers | B2: CT/MDU | C2: Account Manager | D2: 4316.67 | E2: 4316.67 | F2: 4316.67 | G2: 4750 | H2: 4750 | I2: 4300 | J2: 4750 | K2: 5000 | L2: 750 | M2: 4250 | N2: 2000 | O2: 2500 | P2: 8000
A3: Jennifer Raypole | B3: CT/MDU | C3: Account Manager | D3: 1833.34 | E3: 1833.34 | F3: 1833.34 | G3: 3333.33 | H3: 3750 | I3: 2666.66 | J3: 6750 | K3: 9600 | L3: 4550 | M3: 6050 | N3: 3750 | P3: 10300
A4: Constance James | B4: CT/MDU | C4: Account Manager | H4: 3333.33 | I4: 2666.66 | J4: 2000 | K4: 2250 | L4: 3750 | M4: 500 | N4: 1750 | P4: 2750
A5: Guy Huntley | B5: CT/MDU | C5: Account Manager | D5: 3766.66 | E5: 3766.66 | F5: 3766.66 | G5: 2500 | H5: 7000 | I5: 2250 | J5: 2250 | K5: 2250 | L5: 14300 | M5: 4750 | O5: 7500
A6: Steve Norris | B6: CT/MDU | C6: Account Manager | D6: 3333.33 | E6: 3333.33 | F6: 3333.33 | G6: 2000 | H6: 4000 | K6: 5000 | L6: 4500 | M6: 4550 | N6: 750 | O6: 2250 | P6: 2500
A7: Adam Sivertson | B7: CT/MDU | C7: Account Manager | D7: 1666.67 | E7: 1666.67 | F7: 1666.67 | G7: 3750 | H7: 2250 | J7: 6250 | K7: 2500 | L7: 1750 | M7: 8250 | N7: 10000 | O7: 750 | P7: 3250
A8: Amir Planes | B8: CT/MDU | C8: Account Manager | E8: 3000 | F8: 3000 | G8: 3000 | H8: 3000 | I8: 2400 | J8: 1800 | K8: 3000 | L8: 750 | M8: 2500 | N8: 4000 | P8: 4000
A9: Deanna Bethea | B9: CT/MDU | C9: Account Manager | D9: 5266.66 | E9: 5266.66 | F9: 5266.66 | G9: 21100 | H9: 6250 | I9: 5550 | J9: 4850 | K9: 6050 | L9: 8300 | M9: 4500 | N9: 13100 | O9: 2500 | P9: 11050
A10: Morgan Carper | B10: CT/MDU | C10: Market growth specialist/ Account Manager | G10: 2400 | K10: 180 | L10: 3500 | M10: 4550 | O10: 1250
A11: Megan Orf | B11: CT/MDU | C11: Director MDU & Communitities | D11: 4632.71 | E11: 4632.71 | F11: 4632.71 | G11: 6240.45 | H11: 7214.34 | I11: 6498.33 | J11: 8350 | K11: 7804.74 | L11: 5474.92 | M11: 5160.04 | N11: 4347.48 | O11: 3487.11 | P11: 5328.82
A12: Norman Mundy | B12: CT/MDU | C12: Manager TSR | D12: 4583.33 | E12: 4583.33 | F12: 4583.33 | G12: 10125 | H12: 5236.67 | I12: 6289.09 | J12: 8603.64 | K12: 5749 | L12: 4252.17 | M12: 4416.67 | N12: 4182.17 | O12: 4435.33 | P12: 4284.83
A13: David Cutcher | B13: CT/MDU | C13: Sr Mgr, Community Accounts and engagement | D13: 2083 | E13: 4166.67 | F13: 4166.67 | G13: 2310.46 | H13: 4166.67 | I13: 2083 | J13: 4166.66 | K13: 4837.49 | L13: 3831.24 | M13: 368.41 | N13: 3441.14 | O13: 3635.58 | P13: 3603.99
A14: Larry Foster | B14: CT/MDU | C14: Natl Mgr, community fiber expansion | E14: 4583.33 | F14: 4583.33 | G14: 5275 | H14: 7430 | I14: 6243.33 | J14: 8110 | K14: 4444.44 | L14: 4444.44 | M14: 4629.63 | N14: 4074.07 | O14: termed
A15: Connie Williams | B15: CT/MDU | C15: Sales Engineer II | D15: 2083 | E15: 2083 | F15: 2083 | G15: 3083 | H15: 1145.65 | I15: 2083 | J15: 2083 | K15: Moved to AIP 08/01
A16: Tommy Weaver | B16: CT/MDU | C16: Sales Engineer II | D16: 2083 | E16: 2083 | F16: 2083 | G16: 3083 | H16: 1145.65 | I16: 2083 | J16: 2083 | K16: Moved to AIP 08/01
A17: Jared Davis | B17: CT/MDU | C17: Sales Engineer II | D17: 2083 | E17: 2083 | F17: 2083 | G17: 2333 | H17: 2791.26 | I17: 2083 | J17: 2083 | K17: Moved to AIP 08/01
A18: Kelly Kaufman | B18: CT/MDU | C18: Sales Engineer II | D18: 2083 | E18: 2083 | F18: 2083 | G18: 2333 | H18: 2791.26 | I18: 2083 | J18: 2083 | K18: Moved to AIP 08/01
A19: Vince Fletcher | B19: CT/MDU | C19: Sales Engineer II | D19: 2083 | E19: 2083 | F19: 2083 | G19: 1157.2 | H19: 2333 | I19: 2083 | J19: 2083 | K19: Moved to AIP 08/01
A20: Calvin Raymond | B20: CT/MDU | C20: Sales Engineer II | D20: 2083 | E20: 2083 | F20: 2083 | G20: 1157.2 | H20: 2333 | I20: 2083 | J20: 2083 | K20: Moved to AIP 08/01
A21: Freddy Morales | B21: CT/MDU | C21: TSR | H21: 2500 | I21: 4853 | J21: 8856 | K21: 6378 | L21: 3101 | M21: 2348 | N21: 2092 | O21: 2238 | P21: 2436
A22: Joseph Buckles | B22: CT/MDU | C22: TSR | G22: 5106 | H22: 6792 | I22: 7848 | J22: 8520 | K22: 2418 | L22: 2028 | M22: 2168 | N22: 1893 | O22: 1864 | P22: 1969
A23: Karsten Freeman | B23: CT/MDU | C23: TSR | G23: 5405 | H23: 6888 | I23: 7464 | J23: 11712 | K23: 3620 | L23: 2646 | M23: 2308 | N23: 1998 | O23: 1848 | P23: 2308
A24: Owen Stevens | B24: CT/MDU | C24: TSR | G24: 3276 | H24: 4738 | I24: 5290 | J24: 4554 | K24: 2453 | L24: 2144 | M24: 2080 | N24: 1748 | O24: 1800 | P24: 2337
